Workbook
Name cur_month: Dashboard!$F$6
Name cur_year: Dashboard!$F$5

Sheet Dashboard
E5: Year | F5: 2017
E6: Month | F6: Jun
E7: Division
F10: Revenue | N10: Profit | V10: Cash
F11: Actual | H11: % ∆ PY | K11: % ∆ B | N11: Actual | P11: % ∆ PY | S11: % ∆ B | V11: Actual | X11: % ∆ PY | AA11: % ∆ B
D13: =INDEX(Calculation!M15:M$34,Calculation!$D$5) -> 1 | E13: =INDEX(Calculation!N15:N$34,Calculation!$D$5) -> Commuta | F13: =INDEX(Calculation!O15:O$34,Calculation!$D$5) -> 6353 | H13: =INDEX(Calculation!X15:X$34,Calculation!$D$5) -> 0.060070082 | I13: =H13 -> 0.060070082 | K13: =INDEX(Calculation!AA15:AA$34,Calculation!$D$5) -> 0.20436019 | L13: =IF(K13="","",IF(K13>=0.05,"▲",IF(K13<-0.05,"▼",""))) -> ▲ | N13: =INDEX(Calculation!P15:P$34,Calculation!$D$5) -> 762 | P13: =INDEX(Calculation!Y15:Y$34,Calculation!$D$5) -> 0.1305638 | Q13: =P13 -> 0.1305638 | S13: =INDEX(Calculation!AB15:AB$34,Calculation!$D$5) -> 0.3415493 | T13: =IF(S13="","",IF(S13>=0.05,"▲",IF(S13<-0.05,"▼",""))) -> ▲ | V13: =INDEX(Calculation!Q15:Q$34,Calculation!$D$5) -> 7332 | X13: =INDEX(Calculation!Z15:Z$34,Calculation!$D$5) -> 0.023022185 | Y13: =X13 -> 0.023022185 | AA13: =INDEX(Calculation!AC15:AC$34,Calculation!$D$5) -> 0.01452885 | AB13: =IF(AA13="","",IF(AA13>=0.05,"▲",IF(AA13<-0.05,"▼","")))
D14: =INDEX(Calculation!M16:M$34,Calculation!$D$5) -> 2 | E14: =INDEX(Calculation!N16:N$34,Calculation!$D$5) -> Infic | F14: =INDEX(Calculation!O16:O$34,Calculation!$D$5) -> 12373 | H14: =INDEX(Calculation!X16:X$34,Calculation!$D$5) -> -0.0020164543 | I14: =H14 -> -0.0020164543 | K14: =INDEX(Calculation!AA16:AA$34,Calculation!$D$5) -> 0.1815317 | L14: =IF(K14="","",IF(K14>=0.05,"▲",IF(K14<-0.05,"▼",""))) -> ▲ | N14: =INDEX(Calculation!P16:P$34,Calculation!$D$5) -> 408 | P14: =INDEX(Calculation!Y16:Y$34,Calculation!$D$5) -> 0.19648094 | Q14: =P14 -> 0.19648094 | S14: =INDEX(Calculation!AB16:AB$34,Calculation!$D$5) -> -0.11496746 | T14: =IF(S14="","",IF(S14>=0.05,"▲",IF(S14<-0.05,"▼",""))) -> ▼ | V14: =INDEX(Calculation!Q16:Q$34,Calculation!$D$5) -> 3054 | X14: =INDEX(Calculation!Z16:Z$34,Calculation!$D$5) -> 0.0069238378 | Y14: =X14 -> 0.0069238378 | AA14: =INDEX(Calculation!AC16:AC$34,Calculation!$D$5) -> 0.049484536 | AB14: =IF(AA14="","",IF(AA14>=0.05,"▲",IF(AA14<-0.05,"▼","")))
D15: =INDEX(Calculation!M17:M$34,Calculation!$D$5) -> 3 | E15: =INDEX(Calculation!N17:N$34,Calculation!$D$5) -> Accord | F15: =INDEX(Calculation!O17:O$34,Calculation!$D$5) -> 17760 | H15: =INDEX(Calculation!X17:X$34,Calculation!$D$5) -> 0.043171806 | I15: =H15 -> 0.043171806 | K15: =INDEX(Calculation!AA17:AA$34,Calculation!$D$5) -> 0.053755785 | L15: =IF(K15="","",IF(K15>=0.05,"▲",IF(K15<-0.05,"▼",""))) -> ▲ | N15: =INDEX(Calculation!P17:P$34,Calculation!$D$5) -> 800 | P15: =INDEX(Calculation!Y17:Y$34,Calculation!$D$5) -> 0.4084507 | Q15: =P15 -> 0.4084507 | S15: =INDEX(Calculation!AB17:AB$34,Calculation!$D$5) -> 0.3986014 | T15: =IF(S15="","",IF(S15>=0.05,"▲",IF(S15<-0.05,"▼",""))) -> ▲ | V15: =INDEX(Calculation!Q17:Q$34,Calculation!$D$5) -> 6488 | X15: =INDEX(Calculation!Z17:Z$34,Calculation!$D$5) -> -0.13134288 | Y15: =X15 -> -0.13134288 | AA15: =INDEX(Calculation!AC17:AC$34,Calculation!$D$5) -> -0.018605355 | AB15: =IF(AA15="","",IF(AA15>=0.05,"▲",IF(AA15<-0.05,"▼","")))
D16: =INDEX(Calculation!M18:M$34,Calculation!$D$5) -> 4 | E16: =INDEX(Calculation!N18:N$34,Calculation!$D$5) -> Misty Wash | F16: =INDEX(Calculation!O18:O$34,Calculation!$D$5) -> 30399.6 | H16: =INDEX(Calculation!X18:X$34,Calculation!$D$5) -> 0.029392244 | I16: =H16 -> 0.029392244 | K16: =INDEX(Calculation!AA18:AA$34,Calculation!$D$5) -> 0.0053708677 | L16: =IF(K16="","",IF(K16>=0.05,"▲",IF(K16<-0.05,"▼",""))) | N16: =INDEX(Calculation!P18:P$34,Calculation!$D$5) -> 786.8 | P16: =INDEX(Calculation!Y18:Y$34,Calculation!$D$5) -> 0 | Q16: =P16 -> 0 | S16: =INDEX(Calculation!AB18:AB$34,Calculation!$D$5) -> -0.15615616 | T16: =IF(S16="","",IF(S16>=0.05,"▲",IF(S16<-0.05,"▼",""))) -> ▼ | V16: =INDEX(Calculation!Q18:Q$34,Calculation!$D$5) -> 12308.8 | X16: =INDEX(Calculation!Z18:Z$34,Calculation!$D$5) -> -0.11709179 | Y16: =X16 -> -0.11709179 | AA16: =INDEX(Calculation!AC18:AC$34,Calculation!$D$5) -> -0.080142289 | AB16: =IF(AA16="","",IF(AA16>=0.05,"▲",IF(AA16<-0.05,"▼",""))) -> ▼
D17: =INDEX(Calculation!M19:M$34,Calculation!$D$5) -> 5 | E17: =INDEX(Calculation!N19:N$34,Calculation!$D$5) -> Twenty20 | F17: =INDEX(Calculation!O19:O$34,Calculation!$D$5) -> 20400 | H17: =INDEX(Calculation!X19:X$34,Calculation!$D$5) -> -0.082073434 | I17: =H17 -> -0.082073434 | K17: =INDEX(Calculation!AA19:AA$34,Calculation!$D$5) -> 0.10408729 | L17: =IF(K17="","",IF(K17>=0.05,"▲",IF(K17<-0.05,"▼",""))) -> ▲ | N17: =INDEX(Calculation!P19:P$34,Calculation!$D$5) -> 614.4 | P17: =INDEX(Calculation!Y19:Y$34,Calculation!$D$5) -> -0.37864078 | Q17: =P17 -> -0.37864078 | S17: =INDEX(Calculation!AB19:AB$34,Calculation!$D$5) -> -0.45142857 | T17: =IF(S17="","",IF(S17>=0.05,"▲",IF(S17<-0.05,"▼",""))) -> ▼ | V17: =INDEX(Calculation!Q19:Q$34,Calculation!$D$5) -> 15171.2 | X17: =INDEX(Calculation!Z19:Z$34,Calculation!$D$5) -> -0.052936476 | Y17: =X17 -> -0.052936476 | AA17: =INDEX(Calculation!AC19:AC$34,Calculation!$D$5) -> 0.066111986 | AB17: =IF(AA17="","",IF(AA17>=0.05,"▲",IF(AA17<-0.05,"▼",""))) -> ▲
D18: =INDEX(Calculation!M20:M$34,Calculation!$D$5) -> 6 | E18: =INDEX(Calculation!N20:N$34,Calculation!$D$5) -> Tanox | F18: =INDEX(Calculation!O20:O$34,Calculation!$D$5) -> 21088 | H18: =INDEX(Calculation!X20:X$34,Calculation!$D$5) -> 0.068504256 | I18: =H18 -> 0.068504256 | K18: =INDEX(Calculation!AA20:AA$34,Calculation!$D$5) -> 0.10085613 | L18: =IF(K18="","",IF(K18>=0.05,"▲",IF(K18<-0.05,"▼",""))) -> ▲ | N18: =INDEX(Calculation!P20:P$34,Calculation!$D$5) -> 1264 | P18: =INDEX(Calculation!Y20:Y$34,Calculation!$D$5) -> 0.35622318 | Q18: =P18 -> 0.35622318 | S18: =INDEX(Calculation!AB20:AB$34,Calculation!$D$5) -> 0.46976744 | T18: =IF(S18="","",IF(S18>=0.05,"▲",IF(S18<-0.05,"▼",""))) -> ▲ | V18: =INDEX(Calculation!Q20:Q$34,Calculation!$D$5) -> 4828 | X18: =INDEX(Calculation!Z20:Z$34,Calculation!$D$5) -> -0.18720539 | Y18: =X18 -> -0.18720539 | AA18: =INDEX(Calculation!AC20:AC$34,Calculation!$D$5) -> -0.37654959 | AB18: =IF(AA18="","",IF(AA18>=0.05,"▲",IF(AA18<-0.05,"▼",""))) -> ▼
D19: =INDEX(Calculation!M21:M$34,Calculation!$D$5) -> 7 | E19: =INDEX(Calculation!N21:N$34,Calculation!$D$5) -> Minor Liar | F19: =INDEX(Calculation!O21:O$34,Calculation!$D$5) -> 23736.9 | H19: =INDEX(Calculation!X21:X$34,Calculation!$D$5) -> 0.043169293 | I19: =H19 -> 0.043169293 | K19: =INDEX(Calculation!AA21:AA$34,Calculation!$D$5) -> 0.053765016 | L19: =IF(K19="","",IF(K19>=0.05,"▲",IF(K19<-0.05,"▼",""))) -> ▲ | N19: =INDEX(Calculation!P21:P$34,Calculation!$D$5) -> 1012 | P19: =INDEX(Calculation!Y21:Y$34,Calculation!$D$5) -> 0.40888208 | Q19: =P19 -> 0.40888208 | S19: =INDEX(Calculation!AB21:AB$34,Calculation!$D$5) -> 0.39817629 | T19: =IF(S19="","",IF(S19>=0.05,"▲",IF(S19<-0.05,"▼",""))) -> ▲ | V19: =INDEX(Calculation!Q21:Q$34,Calculation!$D$5) -> 8207.1 | X19: =INDEX(Calculation!Z21:Z$34,Calculation!$D$5) -> -0.13133077 | Y19: =X19 -> -0.13133077 | AA19: =INDEX(Calculation!AC21:AC$34,Calculation!$D$5) -> -0.018547751 | AB19: =IF(AA19="","",IF(AA19>=0.05,"▲",IF(AA19<-0.05,"▼","")))
D20: =INDEX(Calculation!M22:M$34,Calculation!$D$5) -> 8 | E20: =INDEX(Calculation!N22:N$34,Calculation!$D$5) -> Mosquit | F20: =INDEX(Calculation!O22:O$34,Calculation!$D$5) -> 6302 | H20: =INDEX(Calculation!X22:X$34,Calculation!$D$5) -> 0.16703704 | I20: =H20 -> 0.16703704 | K20: =INDEX(Calculation!AA22:AA$34,Calculation!$D$5) -> 0.19062913 | L20: =IF(K20="","",IF(K20>=0.05,"▲",IF(K20<-0.05,"▼",""))) -> ▲ | N20: =INDEX(Calculation!P22:P$34,Calculation!$D$5) -> 240 | P20: =INDEX(Calculation!Y22:Y$34,Calculation!$D$5) -> 0.26315789 | Q20: =P20 -> 0.26315789 | S20: =INDEX(Calculation!AB22:AB$34,Calculation!$D$5) -> 0.53846154 | T20: =IF(S20="","",IF(S20>=0.05,"▲",IF(S20<-0.05,"▼",""))) -> ▲ | V20: =INDEX(Calculation!Q22:Q$34,Calculation!$D$5) -> 4655 | X20: =INDEX(Calculation!Z22:Z$34,Calculation!$D$5) -> 0.13647461 | Y20: =X20 -> 0.13647461 | AA20: =INDEX(Calculation!AC22:AC$34,Calculation!$D$5) -> 0.031236154 | AB20: =IF(AA20="","",IF(AA20>=0.05,"▲",IF(AA20<-0.05,"▼","")))
D21: =INDEX(Calculation!M23:M$34,Calculation!$D$5) -> 9 | E21: =INDEX(Calculation!N23:N$34,Calculation!$D$5) -> Atmos | F21: =INDEX(Calculation!O23:O$34,Calculation!$D$5) -> 10675 | H21: =INDEX(Calculation!X23:X$34,Calculation!$D$5) -> 0.053488602 | I21: =H21 -> 0.053488602 | K21: =INDEX(Calculation!AA23:AA$34,Calculation!$D$5) -> -0.044999105 | L21: =IF(K21="","",IF(K21>=0.05,"▲",IF(K21<-0.05,"▼",""))) | N21: =INDEX(Calculation!P23:P$34,Calculation!$D$5) -> 128 | P21: =INDEX(Calculation!Y23:Y$34,Calculation!$D$5) -> 0.43820225 | Q21: =P21 -> 0.43820225 | S21: =INDEX(Calculation!AB23:AB$34,Calculation!$D$5) -> -0.32631579 | T21: =IF(S21="","",IF(S21>=0.05,"▲",IF(S21<-0.05,"▼",""))) -> ▼ | V21: =INDEX(Calculation!Q23:Q$34,Calculation!$D$5) -> 8210 | X21: =INDEX(Calculation!Z23:Z$34,Calculation!$D$5) -> 0.0037901944 | Y21: =X21 -> 0.0037901944 | AA21: =INDEX(Calculation!AC23:AC$34,Calculation!$D$5) -> 0.024968789 | AB21: =IF(AA21="","",IF(AA21>=0.05,"▲",IF(AA21<-0.05,"▼","")))
D22: =INDEX(Calculation!M24:M$34,Calculation!$D$5) -> 10 | E22: =INDEX(Calculation!N24:N$34,Calculation!$D$5) -> Scrap | F22: =INDEX(Calculation!O24:O$34,Calculation!$D$5) -> 13307 | H22: =INDEX(Calculation!X24:X$34,Calculation!$D$5) -> 0.097303538 | I22: =H22 -> 0.097303538 | K22: =INDEX(Calculation!AA24:AA$34,Calculation!$D$5) -> -0.01048483 | L22: =IF(K22="","",IF(K22>=0.05,"▲",IF(K22<-0.05,"▼",""))) | N22: =INDEX(Calculation!P24:P$34,Calculation!$D$5) -> 862 | P22: =INDEX(Calculation!Y24:Y$34,Calculation!$D$5) -> 0.16172507 | Q22: =P22 -> 0.16172507 | S22: =INDEX(Calculation!AB24:AB$34,Calculation!$D$5) -> -0.047513812 | T22: =IF(S22="","",IF(S22>=0.05,"▲",IF(S22<-0.05,"▼",""))) | V22: =INDEX(Calculation!Q24:Q$34,Calculation!$D$5) -> 5279 | X22: =INDEX(Calculation!Z24:Z$34,Calculation!$D$5) -> -0.038608632 | Y22: =X22 -> -0.038608632 | AA22: =INDEX(Calculation!AC24:AC$34,Calculation!$D$5) -> -0.12916529 | AB22: =IF(AA22="","",IF(AA22>=0.05,"▲",IF(AA22<-0.05,"▼",""))) -> ▼

Sheet Calculation
B2: Selected Information (Form controls) | M2: Calculations for scrolling table | AF2: Top 6 / Bottom 6 by KPI | AP2: Profit Line chart | AV2: Data preparation for chart
C4: Selected Division | D4: 3
C5: Table Scroll Position | D5: 1
C6: KPI selection | D6: 1
C7: Top / Bottom Selection | D7: 1
C8: Profit Scroll Position | D8: 1 | O8: =O9&O10&O11&O12 -> 2017JunActualRevenue | P8: =P9&P10&P11&P12 -> 2017JunActualProfit | Q8: =Q9&Q10&Q11&Q12 -> 2017JunActualCash | R8: =R9&R10&R11&R12 -> 2016JunActualRevenue | S8: =S9&S10&S11&S12 -> 2016JunActualProfit | T8: =T9&T10&T11&T12 -> 2016JunActualCash | U8: =U9&U10&U11&U12 -> 2017JunBudgetRevenue | V8: =V9&V10&V11&V12 -> 2017JunBudgetProfit | W8: =W9&W10&W11&W12 -> 2017JunBudgetCash
C9: PY Checkbox | D9: TRUE | O9: =cur_year -> 2017 | P9: =cur_year -> 2017 | Q9: =cur_year -> 2017 | R9: =cur_year-1 -> 2016 | S9: =cur_year-1 -> 2016 | T9: =cur_year-1 -> 2016 | U9: =cur_year -> 2017 | V9: =cur_year -> 2017 | W9: =cur_year -> 2017
C10: Budget Checkbox | D10: TRUE | O10: =cur_month -> Jun | P10: =cur_month -> Jun | Q10: =cur_month -> Jun | R10: =cur_month -> Jun | S10: =cur_month -> Jun | T10: =cur_month -> Jun | U10: =cur_month -> Jun | V10: =cur_month -> Jun | W10: =cur_month -> Jun
O11: Actual | P11: Actual | Q11: Actual | R11: Actual | S11: Actual | T11: Actual | U11: Budget | V11: Budget | W11: Budget | AP11: =INDEX(G14:I34,D8,D4) -> Utility Apps | AV11: ="Profit for "&AP11 -> Profit for Utility Apps
O12: =O14 -> Revenue | P12: =P14 -> Profit | Q12: =Q14 -> Cash | R12: =R14 -> Revenue | S12: =S14 -> Profit | T12: =T14 -> Cash | U12: =U14 -> Revenue | V12: =V14 -> Profit | W12: =W14 -> Cash | AJ12: =CHOOSE(D7,"Top 6","Bottom 6")& " sorted based on % ∆ B" -> Top 6 sorted based on % ∆ B
B13: For Drop-down selections | G13: App to Division Allocation | O13: Actual | R13: PY | U13: Budget | X13: Variance Actual to PY | AA13: Variance Actual to Budget | AF13: Basis - Unsorted | AI13: Sorted | AJ13: ="Actual "&INDEX(O14:Q14,D6)&" Vs. Budget" -> Actual Revenue Vs. Budget | AQ13: =cur_year -> 2017 | AR13: =AQ13-1 -> 2016 | AS13: =AQ13 -> 2017 | AW13: =AQ13 -> 2017 | AX13: =AR13 -> 2016 | AY13: =AS13 -> 2017 | AZ13: Label position
G14: {=TRANSPOSE(C15:C17)} -> Productivity Apps | H14: Game Apps | I14: Utility Apps | M14: Nr. | N14: App | O14: Revenue | P14: Profit | Q14: Cash | R14: Revenue | S14: Profit | T14: Cash | U14: Revenue | V14: Profit | W14: Cash | X14: Revenue% | Y14: Profit% | Z14: Cash% | AA14: Revenue% | AB14: Profit% | AC14: Cash% | AF14: App | AG14: =INDEX(AA14:AC14,D6)&" ∆ B" -> Revenue% ∆ B | AI14: App | AJ14: Actual | AK14: Budget | AL14: Label Position | AM14: Label shown | AP14: Month | AQ14: Actual | AR14: Actual | AS14: Budget | AV14: Month | AW14: =AQ14 -> Actual | AX14: =AR14 -> Actual | AY14: =AS14 -> Budget | AZ14: Actual
B15: Jan | C15: Productivity Apps | D15: Revenue | G15: WenCaL | H15: Fightrr | I15: Commuta | M15: =IF(N15<>"",ROW(A1),"") -> 1 | N15: =IF(INDEX(G15:I15,$D$4)="","",INDEX(G15:I15,$D$4)) -> Commuta | O15: =IF($N15<>"",INDEX(Data!$B$9:$J$60,MATCH($N15,Data!$A$9:$A$60,0),MATCH(O$8,Data!$B$4:$J$4,0)),"") -> 6353 | P15: =IF($N15<>"",INDEX(Data!$B$9:$J$60,MATCH($N15,Data!$A$9:$A$60,0),MATCH(P$8,Data!$B$4:$J$4,0)),"") -> 762 | Q15: =IF($N15<>"",INDEX(Data!$B$9:$J$60,MATCH($N15,Data!$A$9:$A$60,0),MATCH(Q$8,Data!$B$4:$J$4,0)),"") -> 7332 | R15: =IF($N15<>"",INDEX(Data!$B$9:$J$60,MATCH($N15,Data!$A$9:$A$60,0),MATCH(R$8,Data!$B$4:$J$4,0)),"") -> 5993 | S15: =IF($N15<>"",INDEX(Data!$B$9:$J$60,MATCH($N15,Data!$A$9:$A$60,0),MATCH(S$8,Data!$B$4:$J$4,0)),"") -> 674 | T15: =IF($N15<>"",INDEX(Data!$B$9:$J$60,MATCH($N15,Data!$A$9:$A$60,0),MATCH(T$8,Data!$B$4:$J$4,0)),"") -> 7167 | U15: =IF($N15<>"",INDEX(Data!$B$9:$J$60,MATCH($N15,Data!$A$9:$A$60,0),MATCH(U$8,Data!$B$4:$J$4,0)),"") -> 5275 | V15: =IF($N15<>"",INDEX(Data!$B$9:$J$60,MATCH($N15,Data!$A$9:$A$60,0),MATCH(V$8,Data!$B$4:$J$4,0)),"") -> 568 | W15: =IF($N15<>"",INDEX(Data!$B$9:$J$60,MATCH($N15,Data!$A$9:$A$60,0),MATCH(W$8,Data!$B$4:$J$4,0)),"") -> 7227 | X15: =IF($N15<>"",(O15-R15)/R15,"") -> 0.060070082 | Y15: =IF($N15<>"",(P15-S15)/S15,"") -> 0.1305638 | Z15: =IF($N15<>"",(Q15-T15)/T15,"") -> 0.023022185 | AA15: =IF($N15<>"",(O15-U15)/U15,"") -> 0.20436019 | AB15: =IF($N15<>"",(P15-V15)/V15,"") -> 0.3415493 | AC15: =IF($N15<>"",(Q15-W15)/W15,"") -> 0.01452885 | AF15: =N15 -> Commuta | AG15: =IF(AF15="","",INDEX(AA15:AC15,$D$6)+(ROW()/10000000000)+N("the row function is used here to make sure we have unique values to sort")) -> 0.20436019 | AI15: =INDEX($AF$15:$AF$34,MATCH(CHOOSE($D$7,LARGE($AG$15:$AG$34,$M15),SMALL($AG$15:$AG$34,$M15)),$AG$15:$AG$34,0)) -> Commuta | AJ15: =INDEX($O$15:$Q$35,MATCH($AI15,$N$15:$N$34,0),$D$6) -> 6353 | AK15: =INDEX($U$15:$W$35,MATCH($AI15,$N$15:$N$34,0),$D$6) -> 5275 | AL15: =MAX(AJ15:AK15) -> 6353 | AM15: =TEXT(INDEX($AA$15:$AC$34,MATCH(AI15,$N$15:$N$34,0),$D$6),"0%")&" | "&TEXT(AJ15,"#,##0") -> 20% | 6,353 | AP15: Jan | AQ15: =INDEX(Data!$K$9:$AT$60,MATCH(Calculation!$AP$11,Data!$A$9:$A$60,0),MATCH(Calculation!AQ$13&Calculation!$AP15&Calculation!AQ$14,INDEX(Data!$K$5:$AT$5&Data!$K$6:$AT$6&Data!$K$7:$AT$7,),0)) -> 1232.6 | AR15: =INDEX(Data!$K$9:$AT$60,MATCH(Calculation!$AP$11,Data!$A$9:$A$60,0),MATCH(Calculation!AR$13&Calculation!$AP15&Calculation!AR$14,INDEX(Data!$K$5:$AT$5&Data!$K$6:$AT$6&Data!$K$7:$AT$7,),0)) -> 1081.8 | AS15: =INDEX(Data!$K$9:$AT$60,MATCH(Calculation!$AP$11,Data!$A$9:$A$60,0),MATCH(Calculation!AS$13&Calculation!$AP15&Calculation!AS$14,INDEX(Data!$K$5:$AT$5&Data!$K$6:$AT$6&Data!$K$7:$AT$7,),0)) -> 1097.7 | AV15: =LEFT(AP15,1) -> J | AW15: =IF(MATCH(cur_month,$AP$15:$AP$26,0)>=ROWS($AP$15:AP15),AQ15,NA()) -> 1232.6 | AX15: =IF($D$9,AR15,NA()) -> 1081.8 | AY15: =IF($D$10,AS15,NA()) -> 1097.7 | AZ15: =IF(AP15=cur_month,AW15,NA()) -> #N/A
B16: Feb | C16: Game Apps | D16: Profit | G16: Blend | H16: Kryptis | I16: Infic | M16: =IF(N16<>"",ROW(A2),"") -> 2 | N16: =IF(INDEX(G16:I16,$D$4)="","",INDEX(G16:I16,$D$4)) -> Infic | O16: =IF($N16<>"",INDEX(Data!$B$9:$J$60,MATCH($N16,Data!$A$9:$A$60,0),MATCH(O$8,Data!$B$4:$J$4,0)),"") -> 12373 | P16: =IF($N16<>"",INDEX(Data!$B$9:$J$60,MATCH($N16,Data!$A$9:$A$60,0),MATCH(P$8,Data!$B$4:$J$4,0)),"") -> 408 | Q16: =IF($N16<>"",INDEX(Data!$B$9:$J$60,MATCH($N16,Data!$A$9:$A$60,0),MATCH(Q$8,Data!$B$4:$J$4,0)),"") -> 3054 | R16: =IF($N16<>"",INDEX(Data!$B$9:$J$60,MATCH($N16,Data!$A$9:$A$60,0),MATCH(R$8,Data!$B$4:$J$4,0)),"") -> 12398 | S16: =IF($N16<>"",INDEX(Data!$B$9:$J$60,MATCH($N16,Data!$A$9:$A$60,0),MATCH(S$8,Data!$B$4:$J$4,0)),"") -> 341 | T16: =IF($N16<>"",INDEX(Data!$B$9:$J$60,MATCH($N16,Data!$A$9:$A$60,0),MATCH(T$8,Data!$B$4:$J$4,0)),"") -> 3033 | U16: =IF($N16<>"",INDEX(Data!$B$9:$J$60,MATCH($N16,Data!$A$9:$A$60,0),MATCH(U$8,Data!$B$4:$J$4,0)),"") -> 10472 | V16: =IF($N16<>"",INDEX(Data!$B$9:$J$60,MATCH($N16,Data!$A$9:$A$60,0),MATCH(V$8,Data!$B$4:$J$4,0)),"") -> 461 | W16: =IF($N16<>"",INDEX(Data!$B$9:$J$60,MATCH($N16,Data!$A$9:$A$60,0),MATCH(W$8,Data!$B$4:$J$4,0)),"") -> 2910 | X16: =IF($N16<>"",(O16-R16)/R16,"") -> -0.0020164543 | Y16: =IF($N16<>"",(P16-S16)/S16,"") -> 0.19648094 | Z16: =IF($N16<>"",(Q16-T16)/T16,"") -> 0.0069238378 | AA16: =IF($N16<>"",(O16-U16)/U16,"") -> 0.1815317 | AB16: =IF($N16<>"",(P16-V16)/V16,"") -> -0.11496746 | AC16: =IF($N16<>"",(Q16-W16)/W16,"") -> 0.049484536 | AF16: =N16 -> Infic | AG16: =IF(AF16="","",INDEX(AA16:AC16,$D$6)+(ROW()/10000000000)+N("the row function is used here to make sure we have unique values to sort")) -> 0.18153171 | AI16: =INDEX($AF$15:$AF$34,MATCH(CHOOSE($D$7,LARGE($AG$15:$AG$34,$M16),SMALL($AG$15:$AG$34,$M16)),$AG$15:$AG$34,0)) -> Mosquit | AJ16: =INDEX($O$15:$Q$35,MATCH($AI16,$N$15:$N$34,0),$D$6) -> 6302 | AK16: =INDEX($U$15:$W$35,MATCH($AI16,$N$15:$N$34,0),$D$6) -> 5293 | AL16: =MAX(AJ16:AK16) -> 6302 | AM16: =TEXT(INDEX($AA$15:$AC$34,MATCH(AI16,$N$15:$N$34,0),$D$6),"0%")&" | "&TEXT(AJ16,"#,##0") -> 19% | 6,302 | AP16: Feb | AQ16: =INDEX(Data!$K$9:$AT$60,MATCH(Calculation!$AP$11,Data!$A$9:$A$60,0),MATCH(Calculation!AQ$13&Calculation!$AP16&Calculation!AQ$14,INDEX(Data!$K$5:$AT$5&Data!$K$6:$AT$6&Data!$K$7:$AT$7,),0)) -> 2521.8 | AR16: =INDEX(Data!$K$9:$AT$60,MATCH(Calculation!$AP$11,Data!$A$9:$A$60,0),MATCH(Calculation!AR$13&Calculation!$AP16&Calculation!AR$14,INDEX(Data!$K$5:$AT$5&Data!$K$6:$AT$6&Data!$K$7:$AT$7,),0)) -> 1914.2 | AS16: =INDEX(Data!$K$9:$AT$60,MATCH(Calculation!$AP$11,Data!$A$9:$A$60,0),MATCH(Calculation!AS$13&Calculation!$AP16&Calculation!AS$14,INDEX(Data!$K$5:$AT$5&Data!$K$6:$AT$6&Data!$K$7:$AT$7,),0)) -> 2174.8 | AV16: =LEFT(AP16,1) -> F | AW16: =IF(MATCH(cur_month,$AP$15:$AP$26,0)>=ROWS($AP$15:AP16),AQ16,NA()) -> 2521.8 | AX16: =IF($D$9,AR16,NA()) -> 1914.2 | AY16: =IF($D$10,AS16,NA()) -> 2174.8 | AZ16: =IF(AP16=cur_month,AW16,NA()) -> #N/A
B17: Mar | C17: Utility Apps | D17: Cash | G17: Voltage | H17: Perino | I17: Accord | M17: =IF(N17<>"",ROW(A3),"") -> 3 | N17: =IF(INDEX(G17:I17,$D$4)="","",INDEX(G17:I17,$D$4)) -> Accord | O17: =IF($N17<>"",INDEX(Data!$B$9:$J$60,MATCH($N17,Data!$A$9:$A$60,0),MATCH(O$8,Data!$B$4:$J$4,0)),"") -> 17760 | P17: =IF($N17<>"",INDEX(Data!$B$9:$J$60,MATCH($N17,Data!$A$9:$A$60,0),MATCH(P$8,Data!$B$4:$J$4,0)),"") -> 800 | Q17: =IF($N17<>"",INDEX(Data!$B$9:$J$60,MATCH($N17,Data!$A$9:$A$60,0),MATCH(Q$8,Data!$B$4:$J$4,0)),"") -> 6488 | R17: =IF($N17<>"",INDEX(Data!$B$9:$J$60,MATCH($N17,Data!$A$9:$A$60,0),MATCH(R$8,Data!$B$4:$J$4,0)),"") -> 17025 | S17: =IF($N17<>"",INDEX(Data!$B$9:$J$60,MATCH($N17,Data!$A$9:$A$60,0),MATCH(S$8,Data!$B$4:$J$4,0)),"") -> 568 | T17: =IF($N17<>"",INDEX(Data!$B$9:$J$60,MATCH($N17,Data!$A$9:$A$60,0),MATCH(T$8,Data!$B$4:$J$4,0)),"") -> 7469 | U17: =IF($N17<>"",INDEX(Data!$B$9:$J$60,MATCH($N17,Data!$A$9:$A$60,0),MATCH(U$8,Data!$B$4:$J$4,0)),"") -> 16854 | V17: =IF($N17<>"",INDEX(Data!$B$9:$J$60,MATCH($N17,Data!$A$9:$A$60,0),MATCH(V$8,Data!$B$4:$J$4,0)),"") -> 572 | W17: =IF($N17<>"",INDEX(Data!$B$9:$J$60,MATCH($N17,Data!$A$9:$A$60,0),MATCH(W$8,Data!$B$4:$J$4,0)),"") -> 6611 | X17: =IF($N17<>"",(O17-R17)/R17,"") -> 0.043171806 | Y17: =IF($N17<>"",(P17-S17)/S17,"") -> 0.4084507 | Z17: =IF($N17<>"",(Q17-T17)/T17,"") -> -0.13134288 | AA17: =IF($N17<>"",(O17-U17)/U17,"") -> 0.053755785 | AB17: =IF($N17<>"",(P17-V17)/V17,"") -> 0.3986014 | AC17: =IF($N17<>"",(Q17-W17)/W17,"") -> -0.018605355 | AF17: =N17 -> Accord | AG17: =IF(AF17="","",INDEX(AA17:AC17,$D$6)+(ROW()/10000000000)+N("the row function is used here to make sure we have unique values to sort")) -> 0.053755787 | AI17: =INDEX($AF$15:$AF$34,MATCH(CHOOSE($D$7,LARGE($AG$15:$AG$34,$M17),SMALL($AG$15:$AG$34,$M17)),$AG$15:$AG$34,0)) -> Infic | AJ17: =INDEX($O$15:$Q$35,MATCH($AI17,$N$15:$N$34,0),$D$6) -> 12373 | AK17: =INDEX($U$15:$W$35,MATCH($AI17,$N$15:$N$34,0),$D$6) -> 10472 | AL17: =MAX(AJ17:AK17) -> 12373 | AM17: =TEXT(INDEX($AA$15:$AC$34,MATCH(AI17,$N$15:$N$34,0),$D$6),"0%")&" | "&TEXT(AJ17,"#,##0") -> 18% | 12,373 | AP17: Mar | AQ17: =INDEX(Data!$K$9:$AT$60,MATCH(Calculation!$AP$11,Data!$A$9:$A$60,0),MATCH(Calculation!AQ$13&Calculation!$AP17&Calculation!AQ$14,INDEX(Data!$K$5:$AT$5&Data!$K$6:$AT$6&Data!$K$7:$AT$7,),0)) -> 3867.8 | AR17: =INDEX(Data!$K$9:$AT$60,MATCH(Calculation!$AP$11,Data!$A$9:$A$60,0),MATCH(Calculation!AR$13&Calculation!$AP17&Calculation!AR$14,INDEX(Data!$K$5:$AT$5&Data!$K$6:$AT$6&Data!$K$7:$AT$7,),0)) -> 3013.9 | AS17: =INDEX(Data!$K$9:$AT$60,MATCH(Calculation!$AP$11,Data!$A$9:$A$60,0),MATCH(Calculation!AS$13&Calculation!$AP17&Calculation!AS$14,INDEX(Data!$K$5:$AT$5&Data!$K$6:$AT$6&Data!$K$7:$AT$7,),0)) -> 3533.9 | AV17: =LEFT(AP17,1) -> M | AW17: =IF(MATCH(cur_month,$AP$15:$AP$26,0)>=ROWS($AP$15:AP17),AQ17,NA()) -> 3867.8 | AX17: =IF($D$9,AR17,NA()) -> 3013.9 | AY17: =IF($D$10,AS17,NA()) -> 3533.9 | AZ17: =IF(AP17=cur_month,AW17,NA()) -> #N/A
B18: Apr | G18: Inkly | H18: Five Labs | I18: Misty Wash | M18: =IF(N18<>"",ROW(A4),"") -> 4 | N18: =IF(INDEX(G18:I18,$D$4)="","",INDEX(G18:I18,$D$4)) -> Misty Wash | O18: =IF($N18<>"",INDEX(Data!$B$9:$J$60,MATCH($N18,Data!$A$9:$A$60,0),MATCH(O$8,Data!$B$4:$J$4,0)),"") -> 30399.6 | P18: =IF($N18<>"",INDEX(Data!$B$9:$J$60,MATCH($N18,Data!$A$9:$A$60,0),MATCH(P$8,Data!$B$4:$J$4,0)),"") -> 786.8 | Q18: =IF($N18<>"",INDEX(Data!$B$9:$J$60,MATCH($N18,Data!$A$9:$A$60,0),MATCH(Q$8,Data!$B$4:$J$4,0)),"") -> 12308.8 | R18: =IF($N18<>"",INDEX(Data!$B$9:$J$60,MATCH($N18,Data!$A$9:$A$60,0),MATCH(R$8,Data!$B$4:$J$4,0)),"") -> 29531.6 | S18: =IF($N18<>"",INDEX(Data!$B$9:$J$60,MATCH($N18,Data!$A$9:$A$60,0),MATCH(S$8,Data!$B$4:$J$4,0)),"") -> 786.8 | T18: =IF($N18<>"",INDEX(Data!$B$9:$J$60,MATCH($N18,Data!$A$9:$A$60,0),MATCH(T$8,Data!$B$4:$J$4,0)),"") -> 13941.2 | U18: =IF($N18<>"",INDEX(Data!$B$9:$J$60,MATCH($N18,Data!$A$9:$A$60,0),MATCH(U$8,Data!$B$4:$J$4,0)),"") -> 30237.2 | V18: =IF($N18<>"",INDEX(Data!$B$9:$J$60,MATCH($N18,Data!$A$9:$A$60,0),MATCH(V$8,Data!$B$4:$J$4,0)),"") -> 932.4 | W18: =IF($N18<>"",INDEX(Data!$B$9:$J$60,MATCH($N18,Data!$A$9:$A$60,0),MATCH(W$8,Data!$B$4:$J$4,0)),"") -> 13381.2 | X18: =IF($N18<>"",(O18-R18)/R18,"") -> 0.029392244 | Y18: =IF($N18<>"",(P18-S18)/S18,"") -> 0 | Z18: =IF($N18<>"",(Q18-T18)/T18,"") -> -0.11709179 | AA18: =IF($N18<>"",(O18-U18)/U18,"") -> 0.0053708677 | AB18: =IF($N18<>"",(P18-V18)/V18,"") -> -0.15615616 | AC18: =IF($N18<>"",(Q18-W18)/W18,"") -> -0.080142289 | AF18: =N18 -> Misty Wash | AG18: =IF(AF18="","",INDEX(AA18:AC18,$D$6)+(ROW()/10000000000)+N("the row function is used here to make sure we have unique values to sort")) -> 0.0053708695 | AI18: =INDEX($AF$15:$AF$34,MATCH(CHOOSE($D$7,LARGE($AG$15:$AG$34,$M18),SMALL($AG$15:$AG$34,$M18)),$AG$15:$AG$34,0)) -> Motocyco | AJ18: =INDEX($O$15:$Q$35,MATCH($AI18,$N$15:$N$34,0),$D$6) -> 11182 | AK18: =INDEX($U$15:$W$35,MATCH($AI18,$N$15:$N$34,0),$D$6) -> 9952 | AL18: =MAX(AJ18:AK18) -> 11182 | AM18: =TEXT(INDEX($AA$15:$AC$34,MATCH(AI18,$N$15:$N$34,0),$D$6),"0%")&" | "&TEXT(AJ18,"#,##0") -> 12% | 11,182 | AP18: Apr | AQ18: =INDEX(Data!$K$9:$AT$60,MATCH(Calculation!$AP$11,Data!$A$9:$A$60,0),MATCH(Calculation!AQ$13&Calculation!$AP18&Calculation!AQ$14,INDEX(Data!$K$5:$AT$5&Data!$K$6:$AT$6&Data!$K$7:$AT$7,),0)) -> 5348.4 | AR18: =INDEX(Data!$K$9:$AT$60,MATCH(Calculation!$AP$11,Data!$A$9:$A$60,0),MATCH(Calculation!AR$13&Calculation!$AP18&Calculation!AR$14,INDEX(Data!$K$5:$AT$5&Data!$K$6:$AT$6&Data!$K$7:$AT$7,),0)) -> 4416.4 | AS18: =INDEX(Data!$K$9:$AT$60,MATCH(Calculation!$AP$11,Data!$A$9:$A$60,0),MATCH(Calculation!AS$13&Calculation!$AP18&Calculation!AS$14,INDEX(Data!$K$5:$AT$5&Data!$K$6:$AT$6&Data!$K$7:$AT$7,),0)) -> 4717.1 | AV18: =LEFT(AP18,1) -> A | AW18: =IF(MATCH(cur_month,$AP$15:$AP$26,0)>=ROWS($AP$15:AP18),AQ18,NA()) -> 5348.4 | AX18: =IF($D$9,AR18,NA()) -> 4416.4 | AY18: =IF($D$10,AS18,NA()) -> 4717.1 | AZ18: =IF(AP18=cur_month,AW18,NA()) -> #N/A
B19: May | G19: Sleops | H19: Twistrr | I19: Twenty20 | M19: =IF(N19<>"",ROW(A5),"") -> 5 | N19: =IF(INDEX(G19:I19,$D$4)="","",INDEX(G19:I19,$D$4)) -> Twenty20 | O19: =IF($N19<>"",INDEX(Data!$B$9:$J$60,MATCH($N19,Data!$A$9:$A$60,0),MATCH(O$8,Data!$B$4:$J$4,0)),"") -> 20400 | P19: =IF($N19<>"",INDEX(Data!$B$9:$J$60,MATCH($N19,Data!$A$9:$A$60,0),MATCH(P$8,Data!$B$4:$J$4,0)),"") -> 614.4 | Q19: =IF($N19<>"",INDEX(Data!$B$9:$J$60,MATCH($N19,Data!$A$9:$A$60,0),MATCH(Q$8,Data!$B$4:$J$4,0)),"") -> 15171.2 | R19: =IF($N19<>"",INDEX(Data!$B$9:$J$60,MATCH($N19,Data!$A$9:$A$60,0),MATCH(R$8,Data!$B$4:$J$4,0)),"") -> 22224 | S19: =IF($N19<>"",INDEX(Data!$B$9:$J$60,MATCH($N19,Data!$A$9:$A$60,0),MATCH(S$8,Data!$B$4:$J$4,0)),"") -> 988.8 | T19: =IF($N19<>"",INDEX(Data!$B$9:$J$60,MATCH($N19,Data!$A$9:$A$60,0),MATCH(T$8,Data!$B$4:$J$4,0)),"") -> 16019.2 | U19: =IF($N19<>"",INDEX(Data!$B$9:$J$60,MATCH($N19,Data!$A$9:$A$60,0),MATCH(U$8,Data!$B$4:$J$4,0)),"") -> 18476.8 | V19: =IF($N19<>"",INDEX(Data!$B$9:$J$60,MATCH($N19,Data!$A$9:$A$60,0),MATCH(V$8,Data!$B$4:$J$4,0)),"") -> 1120 | W19: =IF($N19<>"",INDEX(Data!$B$9:$J$60,MATCH($N19,Data!$A$9:$A$60,0),MATCH(W$8,Data!$B$4:$J$4,0)),"") -> 14230.4 | X19: =IF($N19<>"",(O19-R19)/R19,"") -> -0.082073434 | Y19: =IF($N19<>"",(P19-S19)/S19,"") -> -0.37864078 | Z19: =IF($N19<>"",(Q19-T19)/T19,"") -> -0.052936476 | AA19: =IF($N19<>"",(O19-U19)/U19,"") -> 0.10408729 | AB19: =IF($N19<>"",(P19-V19)/V19,"") -> -0.45142857 | AC19: =IF($N19<>"",(Q19-W19)/W19,"") -> 0.066111986 | AF19: =N19 -> Twenty20 | AG19: =IF(AF19="","",INDEX(AA19:AC19,$D$6)+(ROW()/10000000000)+N("the row function is used here to make sure we have unique values to sort")) -> 0.10408729 | AI19: =INDEX($AF$15:$AF$34,MATCH(CHOOSE($D$7,LARGE($AG$15:$AG$34,$M19),SMALL($AG$15:$AG$34,$M19)),$AG$15:$AG$34,0)) -> Twenty20 | AJ19: =INDEX($O$15:$Q$35,MATCH($AI19,$N$15:$N$34,0),$D$6) -> 20400 | AK19: =INDEX($U$15:$W$35,MATCH($AI19,$N$15:$N$34,0),$D$6) -> 18476.8 | AL19: =MAX(AJ19:AK19) -> 20400 | AM19: =TEXT(INDEX($AA$15:$AC$34,MATCH(AI19,$N$15:$N$34,0),$D$6),"0%")&" | "&TEXT(AJ19,"#,##0") -> 10% | 20,400 | AP19: May | AQ19: =INDEX(Data!$K$9:$AT$60,MATCH(Calculation!$AP$11,Data!$A$9:$A$60,0),MATCH(Calculation!AQ$13&Calculation!$AP19&Calculation!AQ$14,INDEX(Data!$K$5:$AT$5&Data!$K$6:$AT$6&Data!$K$7:$AT$7,),0)) -> 7289.8 | AR19: =INDEX(Data!$K$9:$AT$60,MATCH(Calculation!$AP$11,Data!$A$9:$A$60,0),MATCH(Calculation!AR$13&Calculation!$AP19&Calculation!AR$14,INDEX(Data!$K$5:$AT$5&Data!$K$6:$AT$6&Data!$K$7:$AT$7,),0)) -> 5770.1 | AS19: =INDEX(Data!$K$9:$AT$60,MATCH(Calculation!$AP$11,Data!$A$9:$A$60,0),MATCH(Calculation!AS$13&Calculation!$AP19&Calculation!AS$14,INDEX(Data!$K$5:$AT$5&Data!$K$6:$AT$6&Data!$K$7:$AT$7,),0)) -> 6398.8 | AV19: =LEFT(AP19,1) -> M | AW19: =IF(MATCH(cur_month,$AP$15:$AP$26,0)>=ROWS($AP$15:AP19),AQ19,NA()) -> 7289.8 | AX19: =IF($D$9,AR19,NA()) -> 5770.1 | AY19: =IF($D$10,AS19,NA()) -> 6398.8 | AZ19: =IF(AP19=cur_month,AW19,NA()) -> #N/A
B20: Jun | G20: Kind Ape | H20: Hackrr | I20: Tanox | M20: =IF(N20<>"",ROW(A6),"") -> 6 | N20: =IF(INDEX(G20:I20,$D$4)="","",INDEX(G20:I20,$D$4)) -> Tanox | O20: =IF($N20<>"",INDEX(Data!$B$9:$J$60,MATCH($N20,Data!$A$9:$A$60,0),MATCH(O$8,Data!$B$4:$J$4,0)),"") -> 21088 | P20: =IF($N20<>"",INDEX(Data!$B$9:$J$60,MATCH($N20,Data!$A$9:$A$60,0),MATCH(P$8,Data!$B$4:$J$4,0)),"") -> 1264 | Q20: =IF($N20<>"",INDEX(Data!$B$9:$J$60,MATCH($N20,Data!$A$9:$A$60,0),MATCH(Q$8,Data!$B$4:$J$4,0)),"") -> 4828 | R20: =IF($N20<>"",INDEX(Data!$B$9:$J$60,MATCH($N20,Data!$A$9:$A$60,0),MATCH(R$8,Data!$B$4:$J$4,0)),"") -> 19736 | S20: =IF($N20<>"",INDEX(Data!$B$9:$J$60,MATCH($N20,Data!$A$9:$A$60,0),MATCH(S$8,Data!$B$4:$J$4,0)),"") -> 932 | T20: =IF($N20<>"",INDEX(Data!$B$9:$J$60,MATCH($N20,Data!$A$9:$A$60,0),MATCH(T$8,Data!$B$4:$J$4,0)),"") -> 5940 | U20: =IF($N20<>"",INDEX(Data!$B$9:$J$60,MATCH($N20,Data!$A$9:$A$60,0),MATCH(U$8,Data!$B$4:$J$4,0)),"") -> 19156 | V20: =IF($N20<>"",INDEX(Data!$B$9:$J$60,MATCH($N20,Data!$A$9:$A$60,0),MATCH(V$8,Data!$B$4:$J$4,0)),"") -> 860 | W20: =IF($N20<>"",INDEX(Data!$B$9:$J$60,MATCH($N20,Data!$A$9:$A$60,0),MATCH(W$8,Data!$B$4:$J$4,0)),"") -> 7744 | X20: =IF($N20<>"",(O20-R20)/R20,"") -> 0.068504256 | Y20: =IF($N20<>"",(P20-S20)/S20,"") -> 0.35622318 | Z20: =IF($N20<>"",(Q20-T20)/T20,"") -> -0.18720539 | AA20: =IF($N20<>"",(O20-U20)/U20,"") -> 0.10085613 | AB20: =IF($N20<>"",(P20-V20)/V20,"") -> 0.46976744 | AC20: =IF($N20<>"",(Q20-W20)/W20,"") -> -0.37654959 | AF20: =N20 -> Tanox | AG20: =IF(AF20="","",INDEX(AA20:AC20,$D$6)+(ROW()/10000000000)+N("the row function is used here to make sure we have unique values to sort")) -> 0.10085613 | AI20: =INDEX($AF$15:$AF$34,MATCH(CHOOSE($D$7,LARGE($AG$15:$AG$34,$M20),SMALL($AG$15:$AG$34,$M20)),$AG$15:$AG$34,0)) -> Tanox | AJ20: =INDEX($O$15:$Q$35,MATCH($AI20,$N$15:$N$34,0),$D$6) -> 21088 | AK20: =INDEX($U$15:$W$35,MATCH($AI20,$N$15:$N$34,0),$D$6) -> 19156 | AL20: =MAX(AJ20:AK20) -> 21088 | AM20: =TEXT(INDEX($AA$15:$AC$34,MATCH(AI20,$N$15:$N$34,0),$D$6),"0%")&" | "&TEXT(AJ20,"#,##0") -> 10% | 21,088 | AP20: Jun | AQ20: =INDEX(Data!$K$9:$AT$60,MATCH(Calculation!$AP$11,Data!$A$9:$A$60,0),MATCH(Calculation!AQ$13&Calculation!$AP20&Calculation!AQ$14,INDEX(Data!$K$5:$AT$5&Data!$K$6:$AT$6&Data!$K$7:$AT$7,),0)) -> 8869.2 | AR20: =INDEX(Data!$K$9:$AT$60,MATCH(Calculation!$AP$11,Data!$A$9:$A$60,0),MATCH(Calculation!AR$13&Calculation!$AP20&Calculation!AR$14,INDEX(Data!$K$5:$AT$5&Data!$K$6:$AT$6&Data!$K$7:$AT$7,),0)) -> 7247.9 | AS20: =INDEX(Data!$K$9:$AT$60,MATCH(Calculation!$AP$11,Data!$A$9:$A$60,0),MATCH(Calculation!AS$13&Calculation!$AP20&Calculation!AS$14,INDEX(Data!$K$5:$AT$5&Data!$K$6:$AT$6&Data!$K$7:$AT$7,),0)) -> 7933.2 | AV20: =LEFT(AP20,1) -> J | AW20: =IF(MATCH(cur_month,$AP$15:$AP$26,0)>=ROWS($AP$15:AP20),AQ20,NA()) -> 8869.2 | AX20: =IF($D$9,AR20,NA()) -> 7247.9 | AY20: =IF($D$10,AS20,NA()) -> 7933.2 | AZ20: =IF(AP20=cur_month,AW20,NA()) -> 8869.2
B21: Jul | G21: Pet Feed | H21: Pes | I21: Minor Liar | M21: =IF(N21<>"",ROW(A7),"") -> 7 | N21: =IF(INDEX(G21:I21,$D$4)="","",INDEX(G21:I21,$D$4)) -> Minor Liar | O21: =IF($N21<>"",INDEX(Data!$B$9:$J$60,MATCH($N21,Data!$A$9:$A$60,0),MATCH(O$8,Data!$B$4:$J$4,0)),"") -> 23736.9 | P21: =IF($N21<>"",INDEX(Data!$B$9:$J$60,MATCH($N21,Data!$A$9:$A$60,0),MATCH(P$8,Data!$B$4:$J$4,0)),"") -> 1012 | Q21: =IF($N21<>"",INDEX(Data!$B$9:$J$60,MATCH($N21,Data!$A$9:$A$60,0),MATCH(Q$8,Data!$B$4:$J$4,0)),"") -> 8207.1 | R21: =IF($N21<>"",INDEX(Data!$B$9:$J$60,MATCH($N21,Data!$A$9:$A$60,0),MATCH(R$8,Data!$B$4:$J$4,0)),"") -> 22754.6 | S21: =IF($N21<>"",INDEX(Data!$B$9:$J$60,MATCH($N21,Data!$A$9:$A$60,0),MATCH(S$8,Data!$B$4:$J$4,0)),"") -> 718.3 | T21: =IF($N21<>"",INDEX(Data!$B$9:$J$60,MATCH($N21,Data!$A$9:$A$60,0),MATCH(T$8,Data!$B$4:$J$4,0)),"") -> 9447.9 | U21: =IF($N21<>"",INDEX(Data!$B$9:$J$60,MATCH($N21,Data!$A$9:$A$60,0),MATCH(U$8,Data!$B$4:$J$4,0)),"") -> 22525.8 | V21: =IF($N21<>"",INDEX(Data!$B$9:$J$60,MATCH($N21,Data!$A$9:$A$60,0),MATCH(V$8,Data!$B$4:$J$4,0)),"") -> 723.8 | W21: =IF($N21<>"",INDEX(Data!$B$9:$J$60,MATCH($N21,Data!$A$9:$A$60,0),MATCH(W$8,Data!$B$4:$J$4,0)),"") -> 8362.2 | X21: =IF($N21<>"",(O21-R21)/R21,"") -> 0.043169293 | Y21: =IF($N21<>"",(P21-S21)/S21,"") -> 0.40888208 | Z21: =IF($N21<>"",(Q21-T21)/T21,"") -> -0.13133077 | AA21: =IF($N21<>"",(O21-U21)/U21,"") -> 0.053765016 | AB21: =IF($N21<>"",(P21-V21)/V21,"") -> 0.39817629 | AC21: =IF($N21<>"",(Q21-W21)/W21,"") -> -0.018547751 | AF21: =N21 -> Minor Liar | AG21: =IF(AF21="","",INDEX(AA21:AC21,$D$6)+(ROW()/10000000000)+N("the row function is used here to make sure we have unique values to sort")) -> 0.053765018 | AP21: Jul | AQ21: =INDEX(Data!$K$9:$AT$60,MATCH(Calculation!$AP$11,Data!$A$9:$A$60,0),MATCH(Calculation!AQ$13&Calculation!$AP21&Calculation!AQ$14,INDEX(Data!$K$5:$AT$5&Data!$K$6:$AT$6&Data!$K$7:$AT$7,),0)) -> 0 | AR21: =INDEX(Data!$K$9:$AT$60,MATCH(Calculation!$AP$11,Data!$A$9:$A$60,0),MATCH(Calculation!AR$13&Calculation!$AP21&Calculation!AR$14,INDEX(Data!$K$5:$AT$5&Data!$K$6:$AT$6&Data!$K$7:$AT$7,),0)) -> 8752.2 | AS21: =INDEX(Data!$K$9:$AT$60,MATCH(Calculation!$AP$11,Data!$A$9:$A$60,0),MATCH(Calculation!AS$13&Calculation!$AP21&Calculation!AS$14,INDEX(Data!$K$5:$AT$5&Data!$K$6:$AT$6&Data!$K$7:$AT$7,),0)) -> 9431.5 | AV21: =LEFT(AP21,1) -> J | AW21: =IF(MATCH(cur_month,$AP$15:$AP$26,0)>=ROWS($AP$15:AP21),AQ21,NA()) -> #N/A | AX21: =IF($D$9,AR21,NA()) -> 8752.2 | AY21: =IF($D$10,AS21,NA()) -> 9431.5 | AZ21: =IF(AP21=cur_month,AW21,NA()) -> #N/A
B22: Aug | G22: Right App | H22: Baden | I22: Mosquit | M22: =IF(N22<>"",ROW(A8),"") -> 8 | N22: =IF(INDEX(G22:I22,$D$4)="","",INDEX(G22:I22,$D$4)) -> Mosquit | O22: =IF($N22<>"",INDEX(Data!$B$9:$J$60,MATCH($N22,Data!$A$9:$A$60,0),MATCH(O$8,Data!$B$4:$J$4,0)),"") -> 6302 | P22: =IF($N22<>"",INDEX(Data!$B$9:$J$60,MATCH($N22,Data!$A$9:$A$60,0),MATCH(P$8,Data!$B$4:$J$4,0)),"") -> 240 | Q22: =IF($N22<>"",INDEX(Data!$B$9:$J$60,MATCH($N22,Data!$A$9:$A$60,0),MATCH(Q$8,Data!$B$4:$J$4,0)),"") -> 4655 | R22: =IF($N22<>"",INDEX(Data!$B$9:$J$60,MATCH($N22,Data!$A$9:$A$60,0),MATCH(R$8,Data!$B$4:$J$4,0)),"") -> 5400 | S22: =IF($N22<>"",INDEX(Data!$B$9:$J$60,MATCH($N22,Data!$A$9:$A$60,0),MATCH(S$8,Data!$B$4:$J$4,0)),"") -> 190 | T22: =IF($N22<>"",INDEX(Data!$B$9:$J$60,MATCH($N22,Data!$A$9:$A$60,0),MATCH(T$8,Data!$B$4:$J$4,0)),"") -> 4096 | U22: =IF($N22<>"",INDEX(Data!$B$9:$J$60,MATCH($N22,Data!$A$9:$A$60,0),MATCH(U$8,Data!$B$4:$J$4,0)),"") -> 5293 | V22: =IF($N22<>"",INDEX(Data!$B$9:$J$60,MATCH($N22,Data!$A$9:$A$60,0),MATCH(V$8,Data!$B$4:$J$4,0)),"") -> 156 | W22: =IF($N22<>"",INDEX(Data!$B$9:$J$60,MATCH($N22,Data!$A$9:$A$60,0),MATCH(W$8,Data!$B$4:$J$4,0)),"") -> 4514 | X22: =IF($N22<>"",(O22-R22)/R22,"") -> 0.16703704 | Y22: =IF($N22<>"",(P22-S22)/S22,"") -> 0.26315789 | Z22: =IF($N22<>"",(Q22-T22)/T22,"") -> 0.13647461 | AA22: =IF($N22<>"",(O22-U22)/U22,"") -> 0.19062913 | AB22: =IF($N22<>"",(P22-V22)/V22,"") -> 0.53846154 | AC22: =IF($N22<>"",(Q22-W22)/W22,"") -> 0.031236154 | AF22: =N22 -> Mosquit | AG22: =IF(AF22="","",INDEX(AA22:AC22,$D$6)+(ROW()/10000000000)+N("the row function is used here to make sure we have unique values to sort")) -> 0.19062914 | AP22: Aug | AQ22: =INDEX(Data!$K$9:$AT$60,MATCH(Calculation!$AP$11,Data!$A$9:$A$60,0),MATCH(Calculation!AQ$13&Calculation!$AP22&Calculation!AQ$14,INDEX(Data!$K$5:$AT$5&Data!$K$6:$AT$6&Data!$K$7:$AT$7,),0)) -> 0 | AR22: =INDEX(Data!$K$9:$AT$60,MATCH(Calculation!$AP$11,Data!$A$9:$A$60,0),MATCH(Calculation!AR$13&Calculation!$AP22&Calculation!AR$14,INDEX(Data!$K$5:$AT$5&Data!$K$6:$AT$6&Data!$K$7:$AT$7,),0)) -> 9323.8 | AS22: =INDEX(Data!$K$9:$AT$60,MATCH(Calculation!$AP$11,Data!$A$9:$A$60,0),MATCH(Calculation!AS$13&Calculation!$AP22&Calculation!AS$14,INDEX(Data!$K$5:$AT$5&Data!$K$6:$AT$6&Data!$K$7:$AT$7,),0)) -> 9732.8 | AV22: =LEFT(AP22,1) -> A | AW22: =IF(MATCH(cur_month,$AP$15:$AP$26,0)>=ROWS($AP$15:AP22),AQ22,NA()) -> #N/A | AX22: =IF($D$9,AR22,NA()) -> 9323.8 | AY22: =IF($D$10,AS22,NA()) -> 9732.8 | AZ22: =IF(AP22=cur_month,AW22,NA()) -> #N/A
B23: Sep | G23: Mirrrr | H23: Jellyfish | I23: Atmos | M23: =IF(N23<>"",ROW(A9),"") -> 9 | N23: =IF(INDEX(G23:I23,$D$4)="","",INDEX(G23:I23,$D$4)) -> Atmos | O23: =IF($N23<>"",INDEX(Data!$B$9:$J$60,MATCH($N23,Data!$A$9:$A$60,0),MATCH(O$8,Data!$B$4:$J$4,0)),"") -> 10675 | P23: =IF($N23<>"",INDEX(Data!$B$9:$J$60,MATCH($N23,Data!$A$9:$A$60,0),MATCH(P$8,Data!$B$4:$J$4,0)),"") -> 128 | Q23: =IF($N23<>"",INDEX(Data!$B$9:$J$60,MATCH($N23,Data!$A$9:$A$60,0),MATCH(Q$8,Data!$B$4:$J$4,0)),"") -> 8210 | R23: =IF($N23<>"",INDEX(Data!$B$9:$J$60,MATCH($N23,Data!$A$9:$A$60,0),MATCH(R$8,Data!$B$4:$J$4,0)),"") -> 10133 | S23: =IF($N23<>"",INDEX(Data!$B$9:$J$60,MATCH($N23,Data!$A$9:$A$60,0),MATCH(S$8,Data!$B$4:$J$4,0)),"") -> 89 | T23: =IF($N23<>"",INDEX(Data!$B$9:$J$60,MATCH($N23,Data!$A$9:$A$60,0),MATCH(T$8,Data!$B$4:$J$4,0)),"") -> 8179 | U23: =IF($N23<>"",INDEX(Data!$B$9:$J$60,MATCH($N23,Data!$A$9:$A$60,0),MATCH(U$8,Data!$B$4:$J$4,0)),"") -> 11178 | V23: =IF($N23<>"",INDEX(Data!$B$9:$J$60,MATCH($N23,Data!$A$9:$A$60,0),MATCH(V$8,Data!$B$4:$J$4,0)),"") -> 190 | W23: =IF($N23<>"",INDEX(Data!$B$9:$J$60,MATCH($N23,Data!$A$9:$A$60,0),MATCH(W$8,Data!$B$4:$J$4,0)),"") -> 8010 | X23: =IF($N23<>"",(O23-R23)/R23,"") -> 0.053488602 | Y23: =IF($N23<>"",(P23-S23)/S23,"") -> 0.43820225 | Z23: =IF($N23<>"",(Q23-T23)/T23,"") -> 0.0037901944 | AA23: =IF($N23<>"",(O23-U23)/U23,"") -> -0.044999105 | AB23: =IF($N23<>"",(P23-V23)/V23,"") -> -0.32631579 | AC23: =IF($N23<>"",(Q23-W23)/W23,"") -> 0.024968789 | AF23: =N23 -> Atmos | AG23: =IF(AF23="","",INDEX(AA23:AC23,$D$6)+(ROW()/10000000000)+N("the row function is used here to make sure we have unique values to sort")) -> -0.044999103 | AP23: Sep | AQ23: =INDEX(Data!$K$9:$AT$60,MATCH(Calculation!$AP$11,Data!$A$9:$A$60,0),MATCH(Calculation!AQ$13&Calculation!$AP23&Calculation!AQ$14,INDEX(Data!$K$5:$AT$5&Data!$K$6:$AT$6&Data!$K$7:$AT$7,),0)) -> 0 | AR23: =INDEX(Data!$K$9:$AT$60,MATCH(Calculation!$AP$11,Data!$A$9:$A$60,0),MATCH(Calculation!AR$13&Calculation!$AP23&Calculation!AR$14,INDEX(Data!$K$5:$AT$5&Data!$K$6:$AT$6&Data!$K$7:$AT$7,),0)) -> 10122.5 | AS23: =INDEX(Data!$K$9:$AT$60,MATCH(Calculation!$AP$11,Data!$A$9:$A$60,0),MATCH(Calculation!AS$13&Calculation!$AP23&Calculation!AS$14,INDEX(Data!$K$5:$AT$5&Data!$K$6:$AT$6&Data!$K$7:$AT$7,),0)) -> 11196.7 | AV23: =LEFT(AP23,1) -> S | AW23: =IF(MATCH(cur_month,$AP$15:$AP$26,0)>=ROWS($AP$15:AP23),AQ23,NA()) -> #N/A | AX23: =IF($D$9,AR23,NA()) -> 10122.5 | AY23: =IF($D$10,AS23,NA()) -> 11196.7 | AZ23: =IF(AP23=cur_month,AW23,NA()) -> #N/A
B24: Oct | G24: Halotot | H24: Aviatrr | I24: Scrap | M24: =IF(N24<>"",ROW(A10),"") -> 10 | N24: =IF(INDEX(G24:I24,$D$4)="","",INDEX(G24:I24,$D$4)) -> Scrap | O24: =IF($N24<>"",INDEX(Data!$B$9:$J$60,MATCH($N24,Data!$A$9:$A$60,0),MATCH(O$8,Data!$B$4:$J$4,0)),"") -> 13307 | P24: =IF($N24<>"",INDEX(Data!$B$9:$J$60,MATCH($N24,Data!$A$9:$A$60,0),MATCH(P$8,Data!$B$4:$J$4,0)),"") -> 862 | Q24: =IF($N24<>"",INDEX(Data!$B$9:$J$60,MATCH($N24,Data!$A$9:$A$60,0),MATCH(Q$8,Data!$B$4:$J$4,0)),"") -> 5279 | R24: =IF($N24<>"",INDEX(Data!$B$9:$J$60,MATCH($N24,Data!$A$9:$A$60,0),MATCH(R$8,Data!$B$4:$J$4,0)),"") -> 12127 | S24: =IF($N24<>"",INDEX(Data!$B$9:$J$60,MATCH($N24,Data!$A$9:$A$60,0),MATCH(S$8,Data!$B$4:$J$4,0)),"") -> 742 | T24: =IF($N24<>"",INDEX(Data!$B$9:$J$60,MATCH($N24,Data!$A$9:$A$60,0),MATCH(T$8,Data!$B$4:$J$4,0)),"") -> 5491 | U24: =IF($N24<>"",INDEX(Data!$B$9:$J$60,MATCH($N24,Data!$A$9:$A$60,0),MATCH(U$8,Data!$B$4:$J$4,0)),"") -> 13448 | V24: =IF($N24<>"",INDEX(Data!$B$9:$J$60,MATCH($N24,Data!$A$9:$A$60,0),MATCH(V$8,Data!$B$4:$J$4,0)),"") -> 905 | W24: =IF($N24<>"",INDEX(Data!$B$9:$J$60,MATCH($N24,Data!$A$9:$A$60,0),MATCH(W$8,Data!$B$4:$J$4,0)),"") -> 6062 | X24: =IF($N24<>"",(O24-R24)/R24,"") -> 0.097303538 | Y24: =IF($N24<>"",(P24-S24)/S24,"") -> 0.16172507 | Z24: =IF($N24<>"",(Q24-T24)/T24,"") -> -0.038608632 | AA24: =IF($N24<>"",(O24-U24)/U24,"") -> -0.01048483 | AB24: =IF($N24<>"",(P24-V24)/V24,"") -> -0.047513812 | AC24: =IF($N24<>"",(Q24-W24)/W24,"") -> -0.12916529 | AF24: =N24 -> Scrap | AG24: =IF(AF24="","",INDEX(AA24:AC24,$D$6)+(ROW()/10000000000)+N("the row function is used here to make sure we have unique values to sort")) -> -0.010484828 | AP24: Oct | AQ24: =INDEX(Data!$K$9:$AT$60,MATCH(Calculation!$AP$11,Data!$A$9:$A$60,0),MATCH(Calculation!AQ$13&Calculation!$AP24&Calculation!AQ$14,INDEX(Data!$K$5:$AT$5&Data!$K$6:$AT$6&Data!$K$7:$AT$7,),0)) -> 0 | AR24: =INDEX(Data!$K$9:$AT$60,MATCH(Calculation!$AP$11,Data!$A$9:$A$60,0),MATCH(Calculation!AR$13&Calculation!$AP24&Calculation!AR$14,INDEX(Data!$K$5:$AT$5&Data!$K$6:$AT$6&Data!$K$7:$AT$7,),0)) -> 10897.7 | AS24: =INDEX(Data!$K$9:$AT$60,MATCH(Calculation!$AP$11,Data!$A$9:$A$60,0),MATCH(Calculation!AS$13&Calculation!$AP24&Calculation!AS$14,INDEX(Data!$K$5:$AT$5&Data!$K$6:$AT$6&Data!$K$7:$AT$7,),0)) -> 12313.3 | AV24: =LEFT(AP24,1) -> O | AW24: =IF(MATCH(cur_month,$AP$15:$AP$26,0)>=ROWS($AP$15:AP24),AQ24,NA()) -> #N/A | AX24: =IF($D$9,AR24,NA()) -> 10897.7 | AY24: =IF($D$10,AS24,NA()) -> 12313.3 | AZ24: =IF(AP24=cur_month,AW24,NA()) -> #N/A
B25: Nov | G25: Flowrrr | H25: deRamblr | I25: Motocyco | M25: =IF(N25<>"",ROW(A11),"") -> 11 | N25: =IF(INDEX(G25:I25,$D$4)="","",INDEX(G25:I25,$D$4)) -> Motocyco | O25: =IF($N25<>"",INDEX(Data!$B$9:$J$60,MATCH($N25,Data!$A$9:$A$60,0),MATCH(O$8,Data!$B$4:$J$4,0)),"") -> 11182 | P25: =IF($N25<>"",INDEX(Data!$B$9:$J$60,MATCH($N25,Data!$A$9:$A$60,0),MATCH(P$8,Data!$B$4:$J$4,0)),"") -> 1193 | Q25: =IF($N25<>"",INDEX(Data!$B$9:$J$60,MATCH($N25,Data!$A$9:$A$60,0),MATCH(Q$8,Data!$B$4:$J$4,0)),"") -> 4311 | R25: =IF($N25<>"",INDEX(Data!$B$9:$J$60,MATCH($N25,Data!$A$9:$A$60,0),MATCH(R$8,Data!$B$4:$J$4,0)),"") -> 10457 | S25: =IF($N25<>"",INDEX(Data!$B$9:$J$60,MATCH($N25,Data!$A$9:$A$60,0),MATCH(S$8,Data!$B$4:$J$4,0)),"") -> 890 | T25: =IF($N25<>"",INDEX(Data!$B$9:$J$60,MATCH($N25,Data!$A$9:$A$60,0),MATCH(T$8,Data!$B$4:$J$4,0)),"") -> 4595 | U25: =IF($N25<>"",INDEX(Data!$B$9:$J$60,MATCH($N25,Data!$A$9:$A$60,0),MATCH(U$8,Data!$B$4:$J$4,0)),"") -> 9952 | V25: =IF($N25<>"",INDEX(Data!$B$9:$J$60,MATCH($N25,Data!$A$9:$A$60,0),MATCH(V$8,Data!$B$4:$J$4,0)),"") -> 810 | W25: =IF($N25<>"",INDEX(Data!$B$9:$J$60,MATCH($N25,Data!$A$9:$A$60,0),MATCH(W$8,Data!$B$4:$J$4,0)),"") -> 4298 | X25: =IF($N25<>"",(O25-R25)/R25,"") -> 0.069331548 | Y25: =IF($N25<>"",(P25-S25)/S25,"") -> 0.34044944 | Z25: =IF($N25<>"",(Q25-T25)/T25,"") -> -0.061806311 | AA25: =IF($N25<>"",(O25-U25)/U25,"") -> 0.12359325 | AB25: =IF($N25<>"",(P25-V25)/V25,"") -> 0.47283951 | AC25: =IF($N25<>"",(Q25-W25)/W25,"") -> 0.0030246626 | AF25: =N25 -> Motocyco | AG25: =IF(AF25="","",INDEX(AA25:AC25,$D$6)+(ROW()/10000000000)+N("the row function is used here to make sure we have unique values to sort")) -> 0.12359325 | AP25: Nov | AQ25: =INDEX(Data!$K$9:$AT$60,MATCH(Calculation!$AP$11,Data!$A$9:$A$60,0),MATCH(Calculation!AQ$13&Calculation!$AP25&Calculation!AQ$14,INDEX(Data!$K$5:$AT$5&Data!$K$6:$AT$6&Data!$K$7:$AT$7,),0)) -> 0 | AR25: =INDEX(Data!$K$9:$AT$60,MATCH(Calculation!$AP$11,Data!$A$9:$A$60,0),MATCH(Calculation!AR$13&Calculation!$AP25&Calculation!AR$14,INDEX(Data!$K$5:$AT$5&Data!$K$6:$AT$6&Data!$K$7:$AT$7,),0)) -> 11759 | AS25: =INDEX(Data!$K$9:$AT$60,MATCH(Calculation!$AP$11,Data!$A$9:$A$60,0),MATCH(Calculation!AS$13&Calculation!$AP25&Calculation!AS$14,INDEX(Data!$K$5:$AT$5&Data!$K$6:$AT$6&Data!$K$7:$AT$7,),0)) -> 13505.4 | AV25: =LEFT(AP25,1) -> N | AW25: =IF(MATCH(cur_month,$AP$15:$AP$26,0)>=ROWS($AP$15:AP25),AQ25,NA()) -> #N/A | AX25: =IF($D$9,AR25,NA()) -> 11759 | AY25: =IF($D$10,AS25,NA()) -> 13505.4 | AZ25: =IF(AP25=cur_month,AW25,NA()) -> #N/A
B26: Dec | G26: Silvrr | H26: Arcade | I26: Amplefio | M26: =IF(N26<>"",ROW(A12),"") -> 12 | N26: =IF(INDEX(G26:I26,$D$4)="","",INDEX(G26:I26,$D$4)) -> Amplefio | O26: =IF($N26<>"",INDEX(Data!$B$9:$J$60,MATCH($N26,Data!$A$9:$A$60,0),MATCH(O$8,Data!$B$4:$J$4,0)),"") -> 8250 | P26: =IF($N26<>"",INDEX(Data!$B$9:$J$60,MATCH($N26,Data!$A$9:$A$60,0),MATCH(P$8,Data!$B$4:$J$4,0)),"") -> 541 | Q26: =IF($N26<>"",INDEX(Data!$B$9:$J$60,MATCH($N26,Data!$A$9:$A$60,0),MATCH(Q$8,Data!$B$4:$J$4,0)),"") -> 5923 | R26: =IF($N26<>"",INDEX(Data!$B$9:$J$60,MATCH($N26,Data!$A$9:$A$60,0),MATCH(R$8,Data!$B$4:$J$4,0)),"") -> 8507 | S26: =IF($N26<>"",INDEX(Data!$B$9:$J$60,MATCH($N26,Data!$A$9:$A$60,0),MATCH(S$8,Data!$B$4:$J$4,0)),"") -> 369 | T26: =IF($N26<>"",INDEX(Data!$B$9:$J$60,MATCH($N26,Data!$A$9:$A$60,0),MATCH(T$8,Data!$B$4:$J$4,0)),"") -> 6622 | U26: =IF($N26<>"",INDEX(Data!$B$9:$J$60,MATCH($N26,Data!$A$9:$A$60,0),MATCH(U$8,Data!$B$4:$J$4,0)),"") -> 8899 | V26: =IF($N26<>"",INDEX(Data!$B$9:$J$60,MATCH($N26,Data!$A$9:$A$60,0),MATCH(V$8,Data!$B$4:$J$4,0)),"") -> 474 | W26: =IF($N26<>"",INDEX(Data!$B$9:$J$60,MATCH($N26,Data!$A$9:$A$60,0),MATCH(W$8,Data!$B$4:$J$4,0)),"") -> 6231 | X26: =IF($N26<>"",(O26-R26)/R26,"") -> -0.030210415 | Y26: =IF($N26<>"",(P26-S26)/S26,"") -> 0.46612466 | Z26: =IF($N26<>"",(Q26-T26)/T26,"") -> -0.10555723 | AA26: =IF($N26<>"",(O26-U26)/U26,"") -> -0.072929543 | AB26: =IF($N26<>"",(P26-V26)/V26,"") -> 0.14135021 | AC26: =IF($N26<>"",(Q26-W26)/W26,"") -> -0.049430268 | AF26: =N26 -> Amplefio | AG26: =IF(AF26="","",INDEX(AA26:AC26,$D$6)+(ROW()/10000000000)+N("the row function is used here to make sure we have unique values to sort")) -> -0.07292954 | AP26: Dec | AQ26: =INDEX(Data!$K$9:$AT$60,MATCH(Calculation!$AP$11,Data!$A$9:$A$60,0),MATCH(Calculation!AQ$13&Calculation!$AP26&Calculation!AQ$14,INDEX(Data!$K$5:$AT$5&Data!$K$6:$AT$6&Data!$K$7:$AT$7,),0)) -> 0 | AR26: =INDEX(Data!$K$9:$AT$60,MATCH(Calculation!$AP$11,Data!$A$9:$A$60,0),MATCH(Calculation!AR$13&Calculation!$AP26&Calculation!AR$14,INDEX(Data!$K$5:$AT$5&Data!$K$6:$AT$6&Data!$K$7:$AT$7,),0)) -> 11946 | AS26: =INDEX(Data!$K$9:$AT$60,MATCH(Calculation!$AP$11,Data!$A$9:$A$60,0),MATCH(Calculation!AS$13&Calculation!$AP26&Calculation!AS$14,INDEX(Data!$K$5:$AT$5&Data!$K$6:$AT$6&Data!$K$7:$AT$7,),0)) -> 13380.7 | AV26: =LEFT(AP26,1) -> D | AW26: =IF(MATCH(cur_month,$AP$15:$AP$26,0)>=ROWS($AP$15:AP26),AQ26,NA()) -> #N/A | AX26: =IF($D$9,AR26,NA()) -> 11946 | AY26: =IF($D$10,AS26,NA()) -> 13380.7 | AZ26: =IF(AP26=cur_month,AW26,NA()) -> #N/A
G27: Dasring | I27: Strex | M27: =IF(N27<>"",ROW(A13),"") -> 13 | N27: =IF(INDEX(G27:I27,$D$4)="","",INDEX(G27:I27,$D$4)) -> Strex | O27: =IF($N27<>"",INDEX(Data!$B$9:$J$60,MATCH($N27,Data!$A$9:$A$60,0),MATCH(O$8,Data!$B$4:$J$4,0)),"") -> 8152 | P27: =IF($N27<>"",INDEX(Data!$B$9:$J$60,MATCH($N27,Data!$A$9:$A$60,0),MATCH(P$8,Data!$B$4:$J$4,0)),"") -> 258 | Q27: =IF($N27<>"",INDEX(Data!$B$9:$J$60,MATCH($N27,Data!$A$9:$A$60,0),MATCH(Q$8,Data!$B$4:$J$4,0)),"") -> 5700 | R27: =IF($N27<>"",INDEX(Data!$B$9:$J$60,MATCH($N27,Data!$A$9:$A$60,0),MATCH(R$8,Data!$B$4:$J$4,0)),"") -> 10832 | S27: =IF($N27<>"",INDEX(Data!$B$9:$J$60,MATCH($N27,Data!$A$9:$A$60,0),MATCH(S$8,Data!$B$4:$J$4,0)),"") -> 577 | T27: =IF($N27<>"",INDEX(Data!$B$9:$J$60,MATCH($N27,Data!$A$9:$A$60,0),MATCH(T$8,Data!$B$4:$J$4,0)),"") -> 5100 | U27: =IF($N27<>"",INDEX(Data!$B$9:$J$60,MATCH($N27,Data!$A$9:$A$60,0),MATCH(U$8,Data!$B$4:$J$4,0)),"") -> 9698 | V27: =IF($N27<>"",INDEX(Data!$B$9:$J$60,MATCH($N27,Data!$A$9:$A$60,0),MATCH(V$8,Data!$B$4:$J$4,0)),"") -> 350 | W27: =IF($N27<>"",INDEX(Data!$B$9:$J$60,MATCH($N27,Data!$A$9:$A$60,0),MATCH(W$8,Data!$B$4:$J$4,0)),"") -> 5200 | X27: =IF($N27<>"",(O27-R27)/R27,"") -> -0.24741507 | Y27: =IF($N27<>"",(P27-S27)/S27,"") -> -0.55285962 | Z27: =IF($N27<>"",(Q27-T27)/T27,"") -> 0.11764706 | AA27: =IF($N27<>"",(O27-U27)/U27,"") -> -0.15941431 | AB27: =IF($N27<>"",(P27-V27)/V27,"") -> -0.26285714 | AC27: =IF($N27<>"",(Q27-W27)/W27,"") -> 0.096153846 | AF27: =N27 -> Strex | AG27: =IF(AF27="","",INDEX(AA27:AC27,$D$6)+(ROW()/10000000000)+N("the row function is used here to make sure we have unique values to sort")) -> -0.15941431
G28: Rehire | M28: =IF(N28<>"",ROW(A14),"") | N28: =IF(INDEX(G28:I28,$D$4)="","",INDEX(G28:I28,$D$4)) | O28: =IF($N28<>"",INDEX(Data!$B$9:$J$60,MATCH($N28,Data!$A$9:$A$60,0),MATCH(O$8,Data!$B$4:$J$4,0)),"") | P28: =IF($N28<>"",INDEX(Data!$B$9:$J$60,MATCH($N28,Data!$A$9:$A$60,0),MATCH(P$8,Data!$B$4:$J$4,0)),"") | Q28: =IF($N28<>"",INDEX(Data!$B$9:$J$60,MATCH($N28,Data!$A$9:$A$60,0),MATCH(Q$8,Data!$B$4:$J$4,0)),"") | R28: =IF($N28<>"",INDEX(Data!$B$9:$J$60,MATCH($N28,Data!$A$9:$A$60,0),MATCH(R$8,Data!$B$4:$J$4,0)),"") | S28: =IF($N28<>"",INDEX(Data!$B$9:$J$60,MATCH($N28,Data!$A$9:$A$60,0),MATCH(S$8,Data!$B$4:$J$4,0)),"") | T28: =IF($N28<>"",INDEX(Data!$B$9:$J$60,MATCH($N28,Data!$A$9:$A$60,0),MATCH(T$8,Data!$B$4:$J$4,0)),"") | U28: =IF($N28<>"",INDEX(Data!$B$9:$J$60,MATCH($N28,Data!$A$9:$A$60,0),MATCH(U$8,Data!$B$4:$J$4,0)),"") | V28: =IF($N28<>"",INDEX(Data!$B$9:$J$60,MATCH($N28,Data!$A$9:$A$60,0),MATCH(V$8,Data!$B$4:$J$4,0)),"") | W28: =IF($N28<>"",INDEX(Data!$B$9:$J$60,MATCH($N28,Data!$A$9:$A$60,0),MATCH(W$8,Data!$B$4:$J$4,0)),"") | X28: =IF($N28<>"",(O28-R28)/R28,"") | Y28: =IF($N28<>"",(P28-S28)/S28,"") | Z28: =IF($N28<>"",(Q28-T28)/T28,"") | AA28: =IF($N28<>"",(O28-U28)/U28,"") | AB28: =IF($N28<>"",(P28-V28)/V28,"") | AC28: =IF($N28<>"",(Q28-W28)/W28,"") | AF28: =N28 | AG28: =IF(AF28="","",INDEX(AA28:AC28,$D$6)+(ROW()/10000000000)+N("the row function is used here to make sure we have unique values to sort"))
G29: Didactic | M29: =IF(N29<>"",ROW(A15),"") | N29: =IF(INDEX(G29:I29,$D$4)="","",INDEX(G29:I29,$D$4)) | O29: =IF($N29<>"",INDEX(Data!$B$9:$J$60,MATCH($N29,Data!$A$9:$A$60,0),MATCH(O$8,Data!$B$4:$J$4,0)),"") | P29: =IF($N29<>"",INDEX(Data!$B$9:$J$60,MATCH($N29,Data!$A$9:$A$60,0),MATCH(P$8,Data!$B$4:$J$4,0)),"") | Q29: =IF($N29<>"",INDEX(Data!$B$9:$J$60,MATCH($N29,Data!$A$9:$A$60,0),MATCH(Q$8,Data!$B$4:$J$4,0)),"") | R29: =IF($N29<>"",INDEX(Data!$B$9:$J$60,MATCH($N29,Data!$A$9:$A$60,0),MATCH(R$8,Data!$B$4:$J$4,0)),"") | S29: =IF($N29<>"",INDEX(Data!$B$9:$J$60,MATCH($N29,Data!$A$9:$A$60,0),MATCH(S$8,Data!$B$4:$J$4,0)),"") | T29: =IF($N29<>"",INDEX(Data!$B$9:$J$60,MATCH($N29,Data!$A$9:$A$60,0),MATCH(T$8,Data!$B$4:$J$4,0)),"") | U29: =IF($N29<>"",INDEX(Data!$B$9:$J$60,MATCH($N29,Data!$A$9:$A$60,0),MATCH(U$8,Data!$B$4:$J$4,0)),"") | V29: =IF($N29<>"",INDEX(Data!$B$9:$J$60,MATCH($N29,Data!$A$9:$A$60,0),MATCH(V$8,Data!$B$4:$J$4,0)),"") | W29: =IF($N29<>"",INDEX(Data!$B$9:$J$60,MATCH($N29,Data!$A$9:$A$60,0),MATCH(W$8,Data!$B$4:$J$4,0)),"") | X29: =IF($N29<>"",(O29-R29)/R29,"") | Y29: =IF($N29<>"",(P29-S29)/S29,"") | Z29: =IF($N29<>"",(Q29-T29)/T29,"") | AA29: =IF($N29<>"",(O29-U29)/U29,"") | AB29: =IF($N29<>"",(P29-V29)/V29,"") | AC29: =IF($N29<>"",(Q29-W29)/W29,"") | AF29: =N29 | AG29: =IF(AF29="","",INDEX(AA29:AC29,$D$6)+(ROW()/10000000000)+N("the row function is used here to make sure we have unique values to sort"))
M30: =IF(N30<>"",ROW(A16),"") | N30: =IF(INDEX(G30:I30,$D$4)="","",INDEX(G30:I30,$D$4)) | O30: =IF($N30<>"",INDEX(Data!$B$9:$J$60,MATCH($N30,Data!$A$9:$A$60,0),MATCH(O$8,Data!$B$4:$J$4,0)),"") | P30: =IF($N30<>"",INDEX(Data!$B$9:$J$60,MATCH($N30,Data!$A$9:$A$60,0),MATCH(P$8,Data!$B$4:$J$4,0)),"") | Q30: =IF($N30<>"",INDEX(Data!$B$9:$J$60,MATCH($N30,Data!$A$9:$A$60,0),MATCH(Q$8,Data!$B$4:$J$4,0)),"") | R30: =IF($N30<>"",INDEX(Data!$B$9:$J$60,MATCH($N30,Data!$A$9:$A$60,0),MATCH(R$8,Data!$B$4:$J$4,0)),"") | S30: =IF($N30<>"",INDEX(Data!$B$9:$J$60,MATCH($N30,Data!$A$9:$A$60,0),MATCH(S$8,Data!$B$4:$J$4,0)),"") | T30: =IF($N30<>"",INDEX(Data!$B$9:$J$60,MATCH($N30,Data!$A$9:$A$60,0),MATCH(T$8,Data!$B$4:$J$4,0)),"") | U30: =IF($N30<>"",INDEX(Data!$B$9:$J$60,MATCH($N30,Data!$A$9:$A$60,0),MATCH(U$8,Data!$B$4:$J$4,0)),"") | V30: =IF($N30<>"",INDEX(Data!$B$9:$J$60,MATCH($N30,Data!$A$9:$A$60,0),MATCH(V$8,Data!$B$4:$J$4,0)),"") | W30: =IF($N30<>"",INDEX(Data!$B$9:$J$60,MATCH($N30,Data!$A$9:$A$60,0),MATCH(W$8,Data!$B$4:$J$4,0)),"") | X30: =IF($N30<>"",(O30-R30)/R30,"") | Y30: =IF($N30<>"",(P30-S30)/S30,"") | Z30: =IF($N30<>"",(Q30-T30)/T30,"") | AA30: =IF($N30<>"",(O30-U30)/U30,"") | AB30: =IF($N30<>"",(P30-V30)/V30,"") | AC30: =IF($N30<>"",(Q30-W30)/W30,"") | AF30: =N30 | AG30: =IF(AF30="","",INDEX(AA30:AC30,$D$6)+(ROW()/10000000000)+N("the row function is used here to make sure we have unique values to sort"))
M31: =IF(N31<>"",ROW(A17),"") | N31: =IF(INDEX(G31:I31,$D$4)="","",INDEX(G31:I31,$D$4)) | O31: =IF($N31<>"",INDEX(Data!$B$9:$J$60,MATCH($N31,Data!$A$9:$A$60,0),MATCH(O$8,Data!$B$4:$J$4,0)),"") | P31: =IF($N31<>"",INDEX(Data!$B$9:$J$60,MATCH($N31,Data!$A$9:$A$60,0),MATCH(P$8,Data!$B$4:$J$4,0)),"") | Q31: =IF($N31<>"",INDEX(Data!$B$9:$J$60,MATCH($N31,Data!$A$9:$A$60,0),MATCH(Q$8,Data!$B$4:$J$4,0)),"") | R31: =IF($N31<>"",INDEX(Data!$B$9:$J$60,MATCH($N31,Data!$A$9:$A$60,0),MATCH(R$8,Data!$B$4:$J$4,0)),"") | S31: =IF($N31<>"",INDEX(Data!$B$9:$J$60,MATCH($N31,Data!$A$9:$A$60,0),MATCH(S$8,Data!$B$4:$J$4,0)),"") | T31: =IF($N31<>"",INDEX(Data!$B$9:$J$60,MATCH($N31,Data!$A$9:$A$60,0),MATCH(T$8,Data!$B$4:$J$4,0)),"") | U31: =IF($N31<>"",INDEX(Data!$B$9:$J$60,MATCH($N31,Data!$A$9:$A$60,0),MATCH(U$8,Data!$B$4:$J$4,0)),"") | V31: =IF($N31<>"",INDEX(Data!$B$9:$J$60,MATCH($N31,Data!$A$9:$A$60,0),MATCH(V$8,Data!$B$4:$J$4,0)),"") | W31: =IF($N31<>"",INDEX(Data!$B$9:$J$60,MATCH($N31,Data!$A$9:$A$60,0),MATCH(W$8,Data!$B$4:$J$4,0)),"") | X31: =IF($N31<>"",(O31-R31)/R31,"") | Y31: =IF($N31<>"",(P31-S31)/S31,"") | Z31: =IF($N31<>"",(Q31-T31)/T31,"") | AA31: =IF($N31<>"",(O31-U31)/U31,"") | AB31: =IF($N31<>"",(P31-V31)/V31,"") | AC31: =IF($N31<>"",(Q31-W31)/W31,"") | AF31: =N31 | AG31: =IF(AF31="","",INDEX(AA31:AC31,$D$6)+(ROW()/10000000000)+N("the row function is used here to make sure we have unique values to sort"))
M32: =IF(N32<>"",ROW(A18),"") | N32: =IF(INDEX(G32:I32,$D$4)="","",INDEX(G32:I32,$D$4)) | O32: =IF($N32<>"",INDEX(Data!$B$9:$J$60,MATCH($N32,Data!$A$9:$A$60,0),MATCH(O$8,Data!$B$4:$J$4,0)),"") | P32: =IF($N32<>"",INDEX(Data!$B$9:$J$60,MATCH($N32,Data!$A$9:$A$60,0),MATCH(P$8,Data!$B$4:$J$4,0)),"") | Q32: =IF($N32<>"",INDEX(Data!$B$9:$J$60,MATCH($N32,Data!$A$9:$A$60,0),MATCH(Q$8,Data!$B$4:$J$4,0)),"") | R32: =IF($N32<>"",INDEX(Data!$B$9:$J$60,MATCH($N32,Data!$A$9:$A$60,0),MATCH(R$8,Data!$B$4:$J$4,0)),"") | S32: =IF($N32<>"",INDEX(Data!$B$9:$J$60,MATCH($N32,Data!$A$9:$A$60,0),MATCH(S$8,Data!$B$4:$J$4,0)),"") | T32: =IF($N32<>"",INDEX(Data!$B$9:$J$60,MATCH($N32,Data!$A$9:$A$60,0),MATCH(T$8,Data!$B$4:$J$4,0)),"") | U32: =IF($N32<>"",INDEX(Data!$B$9:$J$60,MATCH($N32,Data!$A$9:$A$60,0),MATCH(U$8,Data!$B$4:$J$4,0)),"") | V32: =IF($N32<>"",INDEX(Data!$B$9:$J$60,MATCH($N32,Data!$A$9:$A$60,0),MATCH(V$8,Data!$B$4:$J$4,0)),"") | W32: =IF($N32<>"",INDEX(Data!$B$9:$J$60,MATCH($N32,Data!$A$9:$A$60,0),MATCH(W$8,Data!$B$4:$J$4,0)),"") | X32: =IF($N32<>"",(O32-R32)/R32,"") | Y32: =IF($N32<>"",(P32-S32)/S32,"") | Z32: =IF($N32<>"",(Q32-T32)/T32,"") | AA32: =IF($N32<>"",(O32-U32)/U32,"") | AB32: =IF($N32<>"",(P32-V32)/V32,"") | AC32: =IF($N32<>"",(Q32-W32)/W32,"") | AF32: =N32 | AG32: =IF(AF32="","",INDEX(AA32:AC32,$D$6)+(ROW()/10000000000)+N("the row function is used here to make sure we have unique values to sort"))
M33: =IF(N33<>"",ROW(A19),"") | N33: =IF(INDEX(G33:I33,$D$4)="","",INDEX(G33:I33,$D$4)) | O33: =IF($N33<>"",INDEX(Data!$B$9:$J$60,MATCH($N33,Data!$A$9:$A$60,0),MATCH(O$8,Data!$B$4:$J$4,0)),"") | P33: =IF($N33<>"",INDEX(Data!$B$9:$J$60,MATCH($N33,Data!$A$9:$A$60,0),MATCH(P$8,Data!$B$4:$J$4,0)),"") | Q33: =IF($N33<>"",INDEX(Data!$B$9:$J$60,MATCH($N33,Data!$A$9:$A$60,0),MATCH(Q$8,Data!$B$4:$J$4,0)),"") | R33: =IF($N33<>"",INDEX(Data!$B$9:$J$60,MATCH($N33,Data!$A$9:$A$60,0),MATCH(R$8,Data!$B$4:$J$4,0)),"") | S33: =IF($N33<>"",INDEX(Data!$B$9:$J$60,MATCH($N33,Data!$A$9:$A$60,0),MATCH(S$8,Data!$B$4:$J$4,0)),"") | T33: =IF($N33<>"",INDEX(Data!$B$9:$J$60,MATCH($N33,Data!$A$9:$A$60,0),MATCH(T$8,Data!$B$4:$J$4,0)),"") | U33: =IF($N33<>"",INDEX(Data!$B$9:$J$60,MATCH($N33,Data!$A$9:$A$60,0),MATCH(U$8,Data!$B$4:$J$4,0)),"") | V33: =IF($N33<>"",INDEX(Data!$B$9:$J$60,MATCH($N33,Data!$A$9:$A$60,0),MATCH(V$8,Data!$B$4:$J$4,0)),"") | W33: =IF($N33<>"",INDEX(Data!$B$9:$J$60,MATCH($N33,Data!$A$9:$A$60,0),MATCH(W$8,Data!$B$4:$J$4,0)),"") | X33: =IF($N33<>"",(O33-R33)/R33,"") | Y33: =IF($N33<>"",(P33-S33)/S33,"") | Z33: =IF($N33<>"",(Q33-T33)/T33,"") | AA33: =IF($N33<>"",(O33-U33)/U33,"") | AB33: =IF($N33<>"",(P33-V33)/V33,"") | AC33: =IF($N33<>"",(Q33-W33)/W33,"") | AF33: =N33 | AG33: =IF(AF33="","",INDEX(AA33:AC33,$D$6)+(ROW()/10000000000)+N("the row function is used here to make sure we have unique values to sort"))
M34: =IF(N34<>"",ROW(A20),"") | N34: =IF(INDEX(G34:I34,$D$4)="","",INDEX(G34:I34,$D$4)) | O34: =IF($N34<>"",INDEX(Data!$B$9:$J$60,MATCH($N34,Data!$A$9:$A$60,0),MATCH(O$8,Data!$B$4:$J$4,0)),"") | P34: =IF($N34<>"",INDEX(Data!$B$9:$J$60,MATCH($N34,Data!$A$9:$A$60,0),MATCH(P$8,Data!$B$4:$J$4,0)),"") | Q34: =IF($N34<>"",INDEX(Data!$B$9:$J$60,MATCH($N34,Data!$A$9:$A$60,0),MATCH(Q$8,Data!$B$4:$J$4,0)),"") | R34: =IF($N34<>"",INDEX(Data!$B$9:$J$60,MATCH($N34,Data!$A$9:$A$60,0),MATCH(R$8,Data!$B$4:$J$4,0)),"") | S34: =IF($N34<>"",INDEX(Data!$B$9:$J$60,MATCH($N34,Data!$A$9:$A$60,0),MATCH(S$8,Data!$B$4:$J$4,0)),"") | T34: =IF($N34<>"",INDEX(Data!$B$9:$J$60,MATCH($N34,Data!$A$9:$A$60,0),MATCH(T$8,Data!$B$4:$J$4,0)),"") | U34: =IF($N34<>"",INDEX(Data!$B$9:$J$60,MATCH($N34,Data!$A$9:$A$60,0),MATCH(U$8,Data!$B$4:$J$4,0)),"") | V34: =IF($N34<>"",INDEX(Data!$B$9:$J$60,MATCH($N34,Data!$A$9:$A$60,0),MATCH(V$8,Data!$B$4:$J$4,0)),"") | W34: =IF($N34<>"",INDEX(Data!$B$9:$J$60,MATCH($N34,Data!$A$9:$A$60,0),MATCH(W$8,Data!$B$4:$J$4,0)),"") | X34: =IF($N34<>"",(O34-R34)/R34,"") | Y34: =IF($N34<>"",(P34-S34)/S34,"") | Z34: =IF($N34<>"",(Q34-T34)/T34,"") | AA34: =IF($N34<>"",(O34-U34)/U34,"") | AB34: =IF($N34<>"",(P34-V34)/V34,"") | AC34: =IF($N34<>"",(Q34-W34)/W34,"") | AF34: =N34 | AG34: =IF(AF34="","",INDEX(AA34:AC34,$D$6)+(ROW()/10000000000)+N("the row function is used here to make sure we have unique values to sort"))
N36: =INDEX(G14:I14,D4) -> Utility Apps | O36: =IF($N36<>"",INDEX(Data!$B$9:$J$60,MATCH($N36,Data!$A$9:$A$60,0),MATCH(O$8,Data!$B$4:$J$4,0)),"") -> 189978.5 | P36: =IF($N36<>"",INDEX(Data!$B$9:$J$60,MATCH($N36,Data!$A$9:$A$60,0),MATCH(P$8,Data!$B$4:$J$4,0)),"") -> 8869.2 | Q36: =IF($N36<>"",INDEX(Data!$B$9:$J$60,MATCH($N36,Data!$A$9:$A$60,0),MATCH(Q$8,Data!$B$4:$J$4,0)),"") -> 91467.1 | R36: =IF($N36<>"",INDEX(Data!$B$9:$J$60,MATCH($N36,Data!$A$9:$A$60,0),MATCH(R$8,Data!$B$4:$J$4,0)),"") -> 187118.2 | S36: =IF($N36<>"",INDEX(Data!$B$9:$J$60,MATCH($N36,Data!$A$9:$A$60,0),MATCH(S$8,Data!$B$4:$J$4,0)),"") -> 7865.9 | T36: =IF($N36<>"",INDEX(Data!$B$9:$J$60,MATCH($N36,Data!$A$9:$A$60,0),MATCH(T$8,Data!$B$4:$J$4,0)),"") -> 97100.3 | U36: =IF($N36<>"",INDEX(Data!$B$9:$J$60,MATCH($N36,Data!$A$9:$A$60,0),MATCH(U$8,Data!$B$4:$J$4,0)),"") -> 181464.8 | V36: =IF($N36<>"",INDEX(Data!$B$9:$J$60,MATCH($N36,Data!$A$9:$A$60,0),MATCH(V$8,Data!$B$4:$J$4,0)),"") -> 8122.2 | W36: =IF($N36<>"",INDEX(Data!$B$9:$J$60,MATCH($N36,Data!$A$9:$A$60,0),MATCH(W$8,Data!$B$4:$J$4,0)),"") -> 94780.8 | X36: =IF($N36<>"",(O36-R36)/R36,"") -> 0.01528606 | Y36: =IF($N36<>"",(P36-S36)/S36,"") -> 0.12755057 | Z36: =IF($N36<>"",(Q36-T36)/T36,"") -> -0.058014239 | AA36: =IF($N36<>"",(R36-U36)/U36,"") -> 0.031154251 | AB36: =IF($N36<>"",(S36-V36)/V36,"") -> -0.03155549 | AC36: =IF($N36<>"",(T36-W36)/W36,"") -> 0.024472256
N38: Calculations for header | X38: Calculations for data bars in scrolling table
N39: Revenue A-B | O39: =O36-U36 -> 8513.7 | P39: =IF(O39>0,"Over Budget",IF(O39<0,"Under Budget")) -> Over Budget | X39: Min Rev % | Y39: =MIN(X15:X34) -> -0.24741507
N40: Profit A-B | O40: =P36-V36 -> 747 | P40: =IF(O40>0,"Over Budget",IF(O40<0,"Under Budget")) -> Over Budget | X40: Max Rev % | Y40: =MAX(X15:X34) -> 0.16703704
N41: Cash A-B | O41: =Q36-W36 -> -3313.7 | P41: =IF(O41>0,"Over Budget",IF(O41<0,"Under Budget")) -> Under Budget | X41: Min Profit % | Y41: =MIN(Y15:Y34) -> -0.55285962
X42: Max Profit % | Y42: =MAX(Y15:Y34) -> 0.46612466
X43: Min Cash % | Y43: =MIN(Z15:Z34) -> -0.18720539
X44: Max Cash % | Y44: =MAX(Z15:Z34) -> 0.13647461

Sheet Data
A1: Connected to Database via add-in
A2: =cur_year -> 2017 | B2: =A2-1 -> 2016
B3: Actual | E3: Actual PY | H3: Budget | K3: Actual | W3: Actual PY | AI3: Budget
A4: Unique key | B4: =B5&B6&B7&B8 -> 2017JunActualRevenue | C4: =C5&C6&C7&C8 -> 2017JunActualProfit | D4: =D5&D6&D7&D8 -> 2017JunActualCash | E4: =E5&E6&E7&E8 -> 2016JunActualRevenue | F4: =F5&F6&F7&F8 -> 2016JunActualProfit | G4: =G5&G6&G7&G8 -> 2016JunActualCash | H4: =H5&H6&H7&H8 -> 2017JunBudgetRevenue | I4: =I5&I6&I7&I8 -> 2017JunBudgetProfit | ... AT4: =AT5&AT6&AT7&AT8 -> 2017DecBudgetProfit
B5: =$A$2 -> 2017 | C5: =$A$2 -> 2017 | D5: =$A$2 -> 2017 | E5: =$B$2 -> 2016 | F5: =$B$2 -> 2016 | G5: =$B$2 -> 2016 | H5: =$A$2 -> 2017 | I5: =$A$2 -> 2017 | J5: =$A$2 -> 2017 | K5: =$A$2 -> 2017 | L5: =$A$2 -> 2017 | M5: =$A$2 -> 2017 | N5: =$A$2 -> 2017 | O5: =$A$2 -> 2017 | ... V5: =$A$2 -> 2017 | W5: =$B$2 -> 2016 | X5: =$B$2 -> 2016 | Y5: =$B$2 -> 2016 | Z5: =$B$2 -> 2016 | AA5: =$B$2 -> 2016 | AB5: =$B$2 -> 2016 | AC5: =$B$2 -> 2016 | AD5: =$B$2 -> 2016 | ... AH5: =$B$2 -> 2016 | AI5: =$A$2 -> 2017 | AJ5: =$A$2 -> 2017 | AK5: =$A$2 -> 2017 | AL5: =$A$2 -> 2017 | AM5: =$A$2 -> 2017 | AN5: =$A$2 -> 2017 | AO5: =$A$2 -> 2017 | AP5: =$A$2 -> 2017 | ... AT5: =$A$2 -> 2017
B6: =cur_month -> Jun | C6: =cur_month -> Jun | D6: =cur_month -> Jun | E6: =cur_month -> Jun | F6: =cur_month -> Jun | G6: =cur_month -> Jun | H6: =cur_month -> Jun | I6: =cur_month -> Jun | J6: =cur_month -> Jun | K6: Jan | L6: Feb | M6: Mar | N6: Apr | O6: May | P6: Jun | Q6: Jul | R6: Aug | S6: Sep | T6: Oct | U6: Nov | V6: Dec | W6: Jan | X6: Feb | Y6: Mar | Z6: Apr | AA6: May | AB6: Jun | AC6: Jul | AD6: Aug | AE6: Sep | AF6: Oct | AG6: Nov | AH6: Dec | AI6: Jan | AJ6: Feb | AK6: Mar | AL6: Apr | AM6: May | AN6: Jun | AO6: Jul | AP6: Aug | AQ6: Sep | AR6: Oct | AS6: Nov | AT6: Dec
B7: Actual | C7: Actual | D7: Actual | E7: Actual | F7: Actual | G7: Actual | H7: Budget | I7: Budget | J7: Budget | K7: Actual | L7: Actual | M7: Actual | N7: Actual | O7: Actual | P7: Actual | Q7: Actual | R7: Actual | S7: Actual | T7: Actual | U7: Actual | V7: Actual | W7: Actual | X7: Actual | Y7: Actual | Z7: Actual | AA7: Actual | AB7: Actual | AC7: Actual | AD7: Actual | AE7: Actual | AF7: Actual | AG7: Actual | AH7: Actual | AI7: Budget | AJ7: Budget | AK7: Budget | AL7: Budget | AM7: Budget | AN7: Budget | AO7: Budget | AP7: Budget | AQ7: Budget | AR7: Budget | AS7: Budget | AT7: Budget
B8: Revenue | C8: Profit | D8: Cash | E8: Revenue | F8: Profit | G8: Cash | H8: Revenue | I8: Profit | J8: Cash | K8: Profit | L8: Profit | M8: Profit | N8: Profit | O8: Profit | P8: Profit | Q8: Profit | R8: Profit | S8: Profit | T8: Profit | U8: Profit | V8: Profit | W8: Profit | X8: Profit | Y8: Profit | Z8: Profit | AA8: Profit | AB8: Profit | AC8: Profit | AD8: Profit | AE8: Profit | AF8: Profit | AG8: Profit | AH8: Profit | AI8: Profit | AJ8: Profit | AK8: Profit | AL8: Profit | AM8: Profit | AN8: Profit | AO8: Profit | AP8: Profit | AQ8: Profit | AR8: Profit | AS8: Profit | AT8: Profit
A9: Productivity Apps | B9: 162643 | C9: 9359 | D9: 103058 | E9: 159773 | F9: 9241 | G9: 103723 | H9: 164760 | I9: 9443 | J9: 104426 | K9: 1005 | L9: 2218 | M9: 3685 | N9: 5304 | O9: 7477 | P9: 9359 | W9: 1136 | X9: 2193 | Y9: 3803 | Z9: 5307 | AA9: 6687 | AB9: 8231 | AC9: 9662 | AD9: 10821 | AE9: 11926 | AF9: 13136 | AG9: 13951 | AH9: 14067 | AI9: 953 | AJ9: 1990 | AK9: 3619 | AL9: 5170 | AM9: 6762 | AN9: 8451 | AO9: 10075 | AP9: 10901 | AQ9: 12366 | AR9: 13962 | AS9: 15507 | AT9: 15918
A10: WenCaL | B10: 14432 | C10: 240 | D10: 11099 | E10: 13699 | F10: 210 | G10: 12058 | H10: 15113 | I10: 363 | J10: 11468 | K10: 23 | L10: 66 | M10: 171 | N10: 200 | O10: 222 | P10: 240 | W10: 22 | X10: 32 | Y10: 44 | Z10: 54 | AA10: 68 | AB10: 76 | AC10: 89 | AD10: 110 | AE10: 113 | AF10: 191 | AG10: 276 | AH10: 264 | AI10: 49 | AJ10: 92 | AK10: 163 | AL10: 228 | AM10: 299 | AN10: 363 | AO10: 423 | AP10: 483 | AQ10: 535 | AR10: 607 | AS10: 671 | AT10: 582
A11: Blend | B11: 17990 | C11: 1166 | D11: 7137 | E11: 16395 | F11: 1003 | G11: 7423 | H11: 18181 | I11: 1223 | J11: 8196 | K11: 170 | L11: 327 | M11: 512 | N11: 732 | O11: 941 | P11: 1166 | W11: 149 | X11: 274 | Y11: 490 | Z11: 641 | AA11: 823 | AB11: 1003 | AC11: 1164 | AD11: 1272 | AE11: 1395 | AF11: 1538 | AG11: 1712 | AH11: 1750 | AI11: 151 | AJ11: 302 | AK11: 547 | AL11: 772 | AM11: 1002 | AN11: 1223 | AO11: 1402 | AP11: 1507 | AQ11: 1724 | AR11: 1977 | AS11: 2191 | AT11: 2239
A12: Voltage | B12: 15117 | C12: 1613 | D12: 5828 | E12: 14138 | F12: 1200 | G12: 6212 | H12: 13455 | I12: 1400 | J12: 5810 | K12: 150 | L12: 315 | M12: 537 | N12: 795 | O12: 1393 | P12: 1613 | W12: 47 | X12: 144 | Y12: 268 | Z12: 358 | AA12: 430 | AB12: 516 | AC12: 608 | AD12: 710 | AE12: 796 | AF12: 866 | AG12: 990 | AH12: 1000 | AI12: 128 | AJ12: 238 | AK12: 365 | AL12: 489 | AM12: 614 | AN12: 732 | AO12: 864 | AP12: 993 | AQ12: 1129 | AR12: 1270 | AS12: 1404 | AT12: 1460
A13: Inkly | B13: 11154 | C13: 731 | D13: 8008 | E13: 11502 | F13: 499 | G13: 8953 | H13: 12031 | I13: 641 | J13: 8424 | K13: 135 | L13: 239 | M13: 341 | N13: 445 | O13: 623 | P13: 731 | W13: 119 | X13: 139 | Y13: 245 | Z13: 350 | AA13: 410 | AB13: 499 | AC13: 547 | AD13: 520 | AE13: 550 | AF13: 551 | AG13: 573 | AH13: 472 | AI13: 114 | AJ13: 184 | AK13: 287 | AL13: 404 | AM13: 521 | AN13: 641 | AO13: 734 | AP13: 742 | AQ13: 848 | AR13: 956 | AS13: 1065 | AT13: 1065
A14: Sleops | B14: 11022 | C14: 550 | D14: 9000 | E14: 14644 | F14: 780 | G14: 8670 | H14: 13112 | I14: 474 | J14: 8193 | K14: 62 | L14: 144 | M14: 167 | N14: 201 | O14: 319 | P14: 550 | W14: 146 | X14: 307 | Y14: 433 | Z14: 560 | AA14: 669 | AB14: 780 | AC14: 884 | AD14: 1263 | AE14: 1263 | AF14: 1263 | AG14: 1265 | AH14: 1275 | AI14: 36 | AJ14: 154 | AK14: 248 | AL14: 359 | AM14: 441 | AN14: 474 | AO14: 525 | AP14: 587 | AQ14: 649 | AR14: 693 | AS14: 754 | AT14: 714
A15: Kind Ape | B15: 8905 | C15: 469 | D15: 6026 | E15: 8796 | F15: 316 | G15: 6251 | H15: 9096 | I15: 620 | J15: 5804 | K15: 24 | L15: 81 | M15: 150 | N15: 314 | O15: 403 | P15: 469 | W15: 42 | X15: 63 | Y15: 128 | Z15: 142 | AA15: 214 | AB15: 316 | AC15: 419 | AD15: 491 | AE15: 576 | AF15: 644 | AG15: 650 | AH15: 551 | AI15: 100 | AJ15: 204 | AK15: 293 | AL15: 422 | AM15: 513 | AN15: 620 | AO15: 722 | AP15: 748 | AQ15: 846 | AR15: 942 | AS15: 1050 | AT15: 1161
A16: Pet Feed | B16: 16735 | C16: 800 | D16: 10149 | E16: 17503 | F16: 1083 | G16: 10507 | H16: 18207 | I16: 1176 | J16: 10508 | K16: 140 | L16: 280 | M16: 390 | N16: 460 | O16: 670 | P16: 800 | W16: 69 | X16: 194 | Y16: 401 | Z16: 668 | AA16: 864 | AB16: 1083 | AC16: 1363 | AD16: 1364 | AE16: 1483 | AF16: 1720 | AG16: 1909 | AH16: 1913 | AI16: 79 | AJ16: 227 | AK16: 459 | AL16: 700 | AM16: 939 | AN16: 1176 | AO16: 1417 | AP16: 1417 | AQ16: 1605 | AR16: 1928 | AS16: 2257 | AT16: 2428
A17: Right App | B17: 3635 | C17: 96 | D17: 2050 | E17: 2337 | F17: 90 | G17: 1585 | H17: 3579 | I17: 184 | J17: 1396 | K17: 9 | L17: 17 | M17: 20 | N17: 15 | O17: 31 | P17: 96 | W17: 17 | X17: 29 | Y17: 44 | Z17: 45 | AA17: 48 | AB17: 55 | AC17: 58 | AD17: 35 | AE17: 41 | AF17: 138 | AG17: 203 | AH17: 298 | AI17: 31 | AJ17: 61 | AK17: 92 | AL17: 123 | AM17: 153 | AN17: 184 | AO17: 215 | AP17: 245 | AQ17: 276 | AR17: 307 | AS17: 337 | AT17: 368
A18: Mirrrr | B18: 15627 | C18: 1996 | D18: 9397 | E18: 15357 | F18: 1908 | G18: 9702 | H18: 14634 | I18: 1584 | J18: 9527 | K18: 73 | L18: 240 | M18: 626 | N18: 1100 | O18: 1558 | P18: 1996 | W18: 48 | X18: 231 | Y18: 575 | Z18: 968 | AA18: 1432 | AB18: 1908 | AC18: 2413 | AD18: 2869 | AE18: 3230 | AF18: 3594 | AG18: 3595 | AH18: 3600 | AI18: 48 | AJ18: 105 | AK18: 507 | AL18: 791 | AM18: 1165 | AN18: 1584 | AO18: 2015 | AP18: 2350 | AQ18: 2656 | AR18: 2872 | AS18: 3141 | AT18: 3259
A19: Halotot | B19: 7270 | C19: 150 | D19: 8948 | E19: 7119 | F19: 349 | G19: 8520 | H19: 7158 | I19: 120 | J19: 8630 | K19: 19 | L19: 43 | M19: 73 | N19: 80 | O19: 142 | P19: 150 | W19: 46 | X19: 107 | Y19: 190 | Z19: 263 | AA19: 308 | AB19: 349 | AC19: 377 | AD19: 516 | AE19: 566 | AF19: 592 | AG19: 591 | AH19: 593 | AI19: 5 | AJ19: 13 | AK19: 25 | AL19: 29 | AM19: 36 | AN19: 48 | AO19: 60 | AP19: 46 | AQ19: 60 | AR19: 65 | AS19: 61 | AT19: 39
A20: Flowrrr | B20: 5955 | C20: 260 | D20: 5931 | E20: 5612 | F20: 233 | G20: 5128 | H20: 5977 | I20: 210 | J20: 4722 | K20: 30 | L20: 70 | M20: 80 | N20: 110 | O20: 120 | P20: 260 | W20: 88 | X20: 151 | Y20: 200 | Z20: 226 | AA20: 232 | AB20: 233 | AC20: 235 | AD20: 213 | AE20: 236 | AF20: 194 | AG20: 198 | AH20: 200 | AI20: 3 | AJ20: 10 | AK20: 20 | AL20: 23 | AM20: 30 | AN20: 40 | AO20: 49 | AP20: 37 | AQ20: 49 | AR20: 54 | AS20: 53 | AT20: 37
... A24: Didactic | B24: 6405 | C24: 363 | D24: 1389 | E24: 5995 | F24: 268 | G24: 1708 | H24: 5819 | I24: 248 | J24: 2226 | K24: 34 | L24: 80 | M24: 151 | N24: 214 | O24: 283 | P24: 363 | W24: 16 | X24: 37 | Y24: 83 | Z24: 161 | AA24: 192 | AB24: 268 | AC24: 286 | AD24: 269 | AE24: 339 | AF24: 383 | AG24: 367 | AH24: 464 | AI24: 24 | AJ24: 54 | AK24: 100 | AL24: 142 | AM24: 194 | AN24: 248 | AO24: 299 | AP24: 299 | AQ24: 345 | AR24: 391 | AS24: 432 | AT24: 431
A25: Game Apps | B25: 210616 | C25: 12324.3 | D25: 95902.1 | E25: 199893.6 | F25: 9835.9 | G25: 101383.6 | H25: 198526.4 | I25: 11343.8 | J25: 100022.6 | K25: 1523.4 | L25: 3029.7 | M25: 4948.4 | N25: 7267 | O25: 10245.5 | P25: 12324.3 | Q25: 0 | R25: 0 | S25: 0 | T25: 0 | U25: 0 | V25: 0 | W25: 1228 | X25: 2468.7 | Y25: 4022.1 | Z25: 5341.2 | AA25: 6926.7 | AB25: 8526.7 | AC25: 10423.9 | AD25: 10992.9 | AE25: 12312.1 | AF25: 13498.9 | AG25: 14643 | AH25: 15391.9 | AI25: 1469.7 | AJ25: 2920.6 | AK25: 4767.4 | AL25: 6226.3 | AM25: 8272.5 | AN25: 10141.4 | AO25: 12032.1 | AP25: 12476.8 | AQ25: 14357.9 | AR25: 15804.7 | AS25: 17385.6 | AT25: 17750.2
A26: Fightrr | B26: 11649 | C26: 802 | D26: 5956 | E26: 10414 | F26: 536 | G26: 6713 | H26: 10593 | I26: 554 | J26: 6803 | K26: 55 | L26: 58 | M26: 212 | N26: 410 | O26: 638 | P26: 802 | W26: 24 | X26: 123 | Y26: 208 | Z26: 229 | AA26: 397 | AB26: 536 | AC26: 849 | AD26: 791 | AE26: 917 | AF26: 1073 | AG26: 1056 | AH26: 1217 | AI26: 26 | AJ26: 68 | AK26: 125 | AL26: 227 | AM26: 406 | AN26: 554 | AO26: 749 | AP26: 724 | AQ26: 872 | AR26: 973 | AS26: 1028 | AT26: 1064
A27: Kryptis | B27: 7718 | C27: 876 | D27: 8432 | E27: 7282 | F27: 775 | G27: 8242 | H27: 6409 | I27: 654 | J27: 8312 | K27: 69 | L27: 157 | M27: 276 | N27: 455 | O27: 671 | P27: 876 | W27: 55 | X27: 142 | Y27: 250 | Z27: 338 | AA27: 574 | AB27: 775 | AC27: 1075 | AD27: 1146 | AE27: 1360 | AF27: 1567 | AG27: 1733 | AH27: 1709 | AI27: 59 | AJ27: 129 | AK27: 211 | AL27: 315 | AM27: 496 | AN27: 654 | AO27: 835 | AP27: 863 | AQ27: 997 | AR27: 1096 | AS27: 1183 | AT27: 1241
A28: Perino | B28: 15033 | C28: 469 | D28: 3512 | E28: 15064 | F28: 392 | G28: 3488 | H28: 12724 | I28: 530 | J28: 3347 | K28: 100 | L28: 154 | M28: 215 | N28: 280 | O28: 389 | P28: 469 | W28: 2 | X28: 44 | Y28: 102 | Z28: 206 | AA28: 269 | AB28: 392 | AC28: 528 | AD28: 616 | AE28: 724 | AF28: 754 | AG28: 737 | AH28: 702 | AI28: 82 | AJ28: 164 | AK28: 283 | AL28: 353 | AM28: 454 | AN28: 530 | AO28: 648 | AP28: 742 | AQ28: 791 | AR28: 812 | AS28: 763 | AT28: 770
A29: Five Labs | B29: 21579 | C29: 920 | D29: 7461 | E29: 20686 | F29: 653 | G29: 8589 | H29: 20478 | I29: 658 | J29: 7602 | K29: 170 | L29: 316 | M29: 478 | N29: 626 | O29: 788 | P29: 920 | W29: 162 | X29: 292 | Y29: 399 | Z29: 506 | AA29: 593 | AB29: 653 | AC29: 716 | AD29: 728 | AE29: 807 | AF29: 867 | AG29: 938 | AH29: 1028 | AI29: 133 | AJ29: 258 | AK29: 411 | AL29: 409 | AM29: 540 | AN29: 658 | AO29: 747 | AP29: 696 | AQ29: 841 | AR29: 855 | AS29: 994 | AT29: 931
A30: Twistrr | B30: 27210.6 | C30: 2903.4 | D30: 10490.4 | E30: 25448.4 | F30: 2160 | G30: 11181.6 | H30: 24219 | I30: 2520 | J30: 10458 | K30: 270 | L30: 567 | M30: 966.6 | N30: 1431 | O30: 2507.4 | P30: 2903.4 | Q30: 0 | R30: 0 | S30: 0 | T30: 0 | U30: 0 | V30: 0 | W30: 84.6 | X30: 259.2 | Y30: 482.4 | Z30: 644.4 | AA30: 774 | AB30: 928.8 | AC30: 1094.4 | AD30: 1278 | AE30: 1432.8 | AF30: 1558.8 | AG30: 1782 | AH30: 1962 | AI30: 230.4 | AJ30: 428.4 | AK30: 657 | AL30: 880.2 | AM30: 1105.2 | AN30: 1317.6 | AO30: 1555.2 | AP30: 1787.4 | AQ30: 2032.2 | AR30: 2286 | AS30: 2527.2 | AT30: 2628
A31: Hackrr | B31: 18700.5 | C31: 984.9 | D31: 12654.6 | E31: 18471.6 | F31: 663.6 | G31: 13127.1 | H31: 19101.6 | I31: 1302 | J31: 12188.4 | K31: 50.4 | L31: 170.1 | M31: 315 | N31: 659.4 | O31: 846.3 | P31: 984.9 | Q31: 0 | R31: 0 | S31: 0 | T31: 0 | U31: 0 | V31: 0 | W31: 88.2 | X31: 132.3 | Y31: 268.8 | Z31: 298.2 | AA31: 449.4 | AB31: 663.6 | AC31: 879.9 | AD31: 1031.1 | AE31: 1209.6 | AF31: 1352.4 | AG31: 1516.2 | AH31: 1157.1 | AI31: 210 | AJ31: 428.4 | AK31: 615.3 | AL31: 886.2 | AM31: 1077.3 | AN31: 1302 | AO31: 1516.2 | AP31: 1570.8 | AQ31: 1776.6 | AR31: 1978.2 | AS31: 2205 | AT31: 2438.1
A32: Pes | B32: 45315.9 | C32: 1932 | D32: 15668.1 | E32: 43440.6 | F32: 1371.3 | G32: 18036.9 | H32: 43003.8 | I32: 1381.8 | J32: 15964.2 | K32: 357 | L32: 663.6 | M32: 1003.8 | N32: 1314.6 | O32: 1654.8 | P32: 1932 | Q32: 0 | R32: 0 | S32: 0 | T32: 0 | U32: 0 | V32: 0 | W32: 340.2 | X32: 613.2 | Y32: 837.9 | Z32: 1062.6 | AA32: 1245.3 | AB32: 1371.3 | AC32: 1503.6 | AD32: 1528.8 | AE32: 1694.7 | AF32: 1820.7 | AG32: 1969.8 | AH32: 2158.8 | AI32: 279.3 | AJ32: 541.8 | AK32: 863.1 | AL32: 858.9 | AM32: 1134 | AN32: 1381.8 | AO32: 1568.7 | AP32: 1461.6 | AQ32: 1766.1 | AR32: 1795.5 | AS32: 2087.4 | AT32: 1955.1
A33: Baden | B33: 35980 | C33: 2332 | D33: 14274 | E33: 32790 | F33: 2006 | G33: 14846 | H33: 36362 | I33: 2446 | J33: 16392 | K33: 340 | L33: 654 | M33: 1024 | N33: 1464 | O33: 1882 | P33: 2332 | Q33: 0 | R33: 0 | S33: 0 | T33: 0 | U33: 0 | V33: 0 | W33: 298 | X33: 548 | Y33: 980 | Z33: 1282 | AA33: 1646 | AB33: 2006 | AC33: 2328 | AD33: 2544 | AE33: 2790 | AF33: 3076 | AG33: 3424 | AH33: 3876 | AI33: 302 | AJ33: 604 | AK33: 1094 | AL33: 1544 | AM33: 2004 | AN33: 2446 | AO33: 2804 | AP33: 3014 | AQ33: 3448 | AR33: 3954 | AS33: 4382 | AT33: 4478
A34: Jellyfish | B34: 7657 | C34: 276 | D34: 5353 | E34: 5307 | F34: 170 | G34: 4710 | H34: 6431 | I34: 179 | J34: 5191 | K34: 43 | L34: 93 | M34: 115 | N34: 164 | O34: 236 | P34: 276 | W34: 23 | X34: 26 | Y34: 40 | Z34: 79 | AA34: 90 | AB34: 92 | AC34: 113 | AD34: 116 | AE34: 116 | AF34: 126 | AG34: 144 | AH34: 151 | AI34: 9 | AJ34: 14 | AK34: 50 | AL34: 109 | AM34: 165 | AN34: 179 | AO34: 226 | AP34: 234 | AQ34: 249 | AR34: 275 | AS34: 283 | AT34: 296
A35: Aviatrr | B35: 8126 | C35: 321 | D35: 6153 | E35: 9111 | F35: 567 | G35: 5959 | H35: 8642 | I35: 554 | J35: 7382 | K35: 24 | L35: 78 | M35: 145 | N35: 197 | O35: 265 | P35: 321 | W35: 121 | X35: 230 | Y35: 355 | Z35: 451 | AA35: 504 | AB35: 567 | AC35: 600 | AD35: 516 | AE35: 538 | AF35: 541 | AG35: 592 | AH35: 593 | AI35: 96 | AJ35: 186 | AK35: 281 | AL35: 371 | AM35: 465 | AN35: 554 | AO35: 665 | AP35: 671 | AQ35: 763 | AR35: 874 | AS35: 961 | AT35: 983
A36: deRamblr | B36: 5272 | C36: 316 | D36: 1207 | E36: 4934 | F36: 233 | G36: 1485 | H36: 4789 | I36: 215 | J36: 1936 | K36: 28 | L36: 69 | M36: 131 | N36: 186 | O36: 246 | P36: 316 | W36: 14 | X36: 32 | Y36: 72 | Z36: 140 | AA36: 167 | AB36: 233 | AC36: 249 | AD36: 234 | AE36: 294 | AF36: 333 | AG36: 319 | AH36: 403 | AI36: 21 | AJ36: 47 | AK36: 87 | AL36: 123 | AM36: 168 | AN36: 215 | AO36: 260 | AP36: 260 | AQ36: 300 | AR36: 340 | AS36: 376 | AT36: 375
A37: Arcade | B37: 6375 | C37: 192 | D37: 4741 | E37: 6945 | F37: 309 | G37: 5006 | H37: 5774 | I37: 350 | J37: 4447 | K37: 17 | L37: 50 | M37: 67 | N37: 80 | O37: 122 | P37: 192 | W37: 16 | X37: 27 | Y37: 27 | Z37: 105 | AA37: 218 | AB37: 309 | AC37: 488 | AD37: 464 | AE37: 429 | AF37: 430 | AG37: 432 | AH37: 435 | AI37: 22 | AJ37: 52 | AK37: 90 | AL37: 150 | AM37: 258 | AN37: 350 | AO37: 458 | AP37: 453 | AQ37: 522 | AR37: 566 | AS37: 596 | AT37: 591
A38: Utility Apps | B38: 189978.5 | C38: 8869.2 | D38: 91467.1 | E38: 187118.2 | F38: 7865.9 | G38: 97100.3 | H38: 181464.8 | I38: 8122.2 | J38: 94780.8 | K38: 1232.6 | L38: 2521.8 | M38: 3867.8 | N38: 5348.4 | O38: 7289.8 | P38: 8869.2 | Q38: 0 | R38: 0 | S38: 0 | T38: 0 | U38: 0 | V38: 0 | W38: 1081.8 | X38: 1914.2 | Y38: 3013.9 | Z38: 4416.4 | AA38: 5770.1 | AB38: 7247.9 | AC38: 8752.2 | AD38: 9323.8 | AE38: 10122.5 | AF38: 10897.7 | AG38: 11759 | AH38: 11946 | AI38: 1097.7 | AJ38: 2174.8 | AK38: 3533.9 | AL38: 4717.1 | AM38: 6398.8 | AN38: 7933.2 | AO38: 9431.5 | AP38: 9732.8 | AQ38: 11196.7 | AR38: 12313.3 | AS38: 13505.4 | AT38: 13380.7
A39: Commuta | B39: 6353 | C39: 762 | D39: 7332 | E39: 5993 | F39: 674 | G39: 7167 | H39: 5275 | I39: 568 | J39: 7227 | K39: 56 | L39: 137 | M39: 240 | N39: 396 | O39: 584 | P39: 762 | W39: 48 | X39: 123 | Y39: 218 | Z39: 294 | AA39: 499 | AB39: 674 | AC39: 934 | AD39: 996 | AE39: 1182 | AF39: 1362 | AG39: 1507 | AH39: 1486 | AI39: 51 | AJ39: 112 | AK39: 183 | AL39: 274 | AM39: 432 | AN39: 568 | AO39: 726 | AP39: 750 | AQ39: 867 | AR39: 953 | AS39: 1029 | AT39: 1079
A40: Infic | B40: 12373 | C40: 408 | D40: 3054 | E40: 12398 | F40: 341 | G40: 3033 | H40: 10472 | I40: 461 | J40: 2910 | K40: 82 | L40: 134 | M40: 187 | N40: 244 | O40: 338 | P40: 408 | W40: 2 | X40: 38 | Y40: 89 | Z40: 179 | AA40: 234 | AB40: 341 | AC40: 459 | AD40: 536 | AE40: 629 | AF40: 656 | AG40: 641 | AH40: 550 | AI40: 71 | AJ40: 142 | AK40: 247 | AL40: 307 | AM40: 395 | AN40: 461 | AO40: 564 | AP40: 645 | AQ40: 688 | AR40: 706 | AS40: 664 | AT40: 593
A41: Accord | B41: 17760 | C41: 800 | D41: 6488 | E41: 17025 | F41: 568 | G41: 7469 | H41: 16854 | I41: 572 | J41: 6611 | K41: 140 | L41: 274 | M41: 416 | N41: 544 | O41: 685 | P41: 800 | W41: 141 | X41: 254 | Y41: 347 | Z41: 440 | AA41: 515 | AB41: 568 | AC41: 623 | AD41: 633 | AE41: 702 | AF41: 754 | AG41: 816 | AH41: 894 | AI41: 116 | AJ41: 225 | AK41: 357 | AL41: 356 | AM41: 470 | AN41: 572 | AO41: 650 | AP41: 606 | AQ41: 732 | AR41: 744 | AS41: 865 | AT41: 810
A42: Misty Wash | B42: 30399.6 | C42: 786.8 | D42: 12308.8 | E42: 29531.6 | F42: 786.8 | G42: 13941.2 | H42: 30237.2 | I42: 932.4 | J42: 13381.2 | K42: 165.2 | L42: 305.2 | M42: 383.6 | N42: 534.8 | O42: 649.6 | P42: 786.8 | Q42: 0 | R42: 0 | S42: 0 | T42: 0 | U42: 0 | V42: 0 | W42: 190.4 | X42: 243.6 | Y42: 383.6 | Z42: 492.8 | AA42: 613.2 | AB42: 786.8 | AC42: 826 | AD42: 949.2 | AE42: 1000 | AF42: 1100 | AG42: 1300 | AH42: 1400 | AI42: 196 | AJ42: 327.6 | AK42: 422.8 | AL42: 599.2 | AM42: 739.2 | AN42: 932.4 | AO42: 1047.2 | AP42: 1083.6 | AQ42: 1285.2 | AR42: 1489.6 | AS42: 1696.8 | AT42: 1744.4
A43: Twenty20 | B43: 20400 | C43: 614.4 | D43: 15171.2 | E43: 22224 | F43: 988.8 | G43: 16019.2 | H43: 18476.8 | I43: 1120 | J43: 14230.4 | K43: 54.4 | L43: 160 | M43: 214.4 | N43: 256 | O43: 390.4 | P43: 614.4 | Q43: 0 | R43: 0 | S43: 0 | T43: 0 | U43: 0 | V43: 0 | W43: 51.2 | X43: 86.4 | Y43: 86.4 | Z43: 336 | AA43: 697.6 | AB43: 988.8 | AC43: 1561.6 | AD43: 1484.8 | AE43: 1372.8 | AF43: 1370 | AG43: 1375 | AH43: 1410 | AI43: 70.4 | AJ43: 166.4 | AK43: 288 | AL43: 480 | AM43: 825.6 | AN43: 1120 | AO43: 1465.6 | AP43: 1449.6 | AQ43: 1670.4 | AR43: 1811.2 | AS43: 1907.2 | AT43: 1891.2
A44: Tanox | B44: 21088 | C44: 1264 | D44: 4828 | E44: 19736 | F44: 932 | G44: 5940 | H44: 19156 | I44: 860 | J44: 7744 | K44: 112 | L44: 276 | M44: 524 | N44: 744 | O44: 984 | P44: 1264 | Q44: 0 | R44: 0 | S44: 0 | T44: 0 | U44: 0 | V44: 0 | W44: 56 | X44: 128 | Y44: 288 | Z44: 560 | AA44: 668 | AB44: 932 | AC44: 996 | AD44: 936 | AE44: 1176 | AF44: 1332 | AG44: 1276 | AH44: 1400 | AI44: 84 | AJ44: 188 | AK44: 348 | AL44: 492 | AM44: 672 | AN44: 860 | AO44: 1040 | AP44: 1040 | AQ44: 1200 | AR44: 1360 | AS44: 1504 | AT44: 1500
A45: Minor Liar | B45: 23736.9 | C45: 1012 | D45: 8207.1 | E45: 22754.6 | F45: 718.3 | G45: 9447.9 | H45: 22525.8 | I45: 723.8 | J45: 8362.2 | K45: 187 | L45: 347.6 | M45: 525.8 | N45: 688.6 | O45: 866.8 | P45: 1012 | Q45: 0 | R45: 0 | S45: 0 | T45: 0 | U45: 0 | V45: 0 | W45: 178.2 | X45: 321.2 | Y45: 438.9 | Z45: 556.6 | AA45: 652.3 | AB45: 718.3 | AC45: 787.6 | AD45: 800.8 | AE45: 887.7 | AF45: 953.7 | AG45: 1100 | AH45: 1120 | AI45: 146.3 | AJ45: 283.8 | AK45: 452.1 | AL45: 449.9 | AM45: 594 | AN45: 723.8 | AO45: 821.7 | AP45: 765.6 | AQ45: 925.1 | AR45: 940.5 | AS45: 1093.4 | AT45: 1024.1
A46: Mosquit | B46: 6302 | C46: 240 | D46: 4655 | E46: 5400 | F46: 190 | G46: 4096 | H46: 5293 | I46: 156 | J46: 4514 | K46: 36 | L46: 81 | M46: 100 | N46: 143 | O46: 205 | P46: 240 | W46: 20 | X46: 22 | Y46: 35 | Z46: 68 | AA46: 78 | AB46: 80 | AC46: 98 | AD46: 101 | AE46: 101 | AF46: 110 | AG46: 126 | AH46: 127 | AI46: 8 | AJ46: 12 | AK46: 44 | AL46: 94 | AM46: 143 | AN46: 156 | AO46: 197 | AP46: 204 | AQ46: 216 | AR46: 239 | AS46: 246 | AT46: 257
A47: Atmos | B47: 10675 | C47: 128 | D47: 8210 | E47: 10133 | F47: 89 | G47: 8179 | H47: 11178 | I47: 190 | J47: 8010 | K47: 17 | L47: 49 | M47: 126 | N47: 190 | O47: 164 | P47: 128 | W47: 55 | X47: 59 | Y47: 66 | Z47: 78 | AA47: 88 | AB47: 89 | AC47: 98 | AD47: 102 | AE47: 110 | AF47: 141 | AG47: 204 | AH47: 204 | AI47: 36 | AJ47: 68 | AK47: 121 | AL47: 168 | AM47: 221 | AN47: 269 | AO47: 313 | AP47: 357 | AQ47: 396 | AR47: 449 | AS47: 497 | AT47: 430
A48: Scrap | B48: 13307 | C48: 862 | D48: 5279 | E48: 12127 | F48: 742 | G48: 5491 | H48: 13448 | I48: 905 | J48: 6062 | K48: 126 | L48: 242 | M48: 379 | N48: 542 | O48: 696 | P48: 862 | W48: 110 | X48: 202 | Y48: 363 | Z48: 474 | AA48: 609 | AB48: 742 | AC48: 861 | AD48: 941 | AE48: 1032 | AF48: 1138 | AG48: 1266 | AH48: 1270 | AI48: 112 | AJ48: 224 | AK48: 405 | AL48: 571 | AM48: 741 | AN48: 905 | AO48: 1037 | AP48: 1115 | AQ48: 1275 | AR48: 1462 | AS48: 1620 | AT48: 1656
A49: Motocyco | B49: 11182 | C49: 1193 | D49: 4311 | E49: 10457 | F49: 890 | G49: 4595 | H49: 9952 | I49: 810 | J49: 4298 | K49: 111 | L49: 233 | M49: 397 | N49: 588 | O49: 1030 | P49: 1193 | W49: 34 | X49: 107 | Y49: 198 | Z49: 265 | AA49: 318 | AB49: 382 | AC49: 450 | AD49: 525 | AE49: 589 | AF49: 640 | AG49: 733 | AH49: 806 | AI49: 95 | AJ49: 176 | AK49: 270 | AL49: 362 | AM49: 454 | AN49: 542 | AO49: 639 | AP49: 734 | AQ49: 835 | AR49: 939 | AS49: 1038 | AT49: 1080
A50: Amplefio | B50: 8250 | C50: 541 | D50: 5923 | E50: 8507 | F50: 369 | G50: 6622 | H50: 8899 | I50: 474 | J50: 6231 | K50: 100 | L50: 177 | M50: 252 | N50: 329 | O50: 461 | P50: 541 | W50: 88 | X50: 103 | Y50: 181 | Z50: 259 | AA50: 303 | AB50: 369 | AC50: 404 | AD50: 385 | AE50: 407 | AF50: 407 | AG50: 424 | AH50: 349 | AI50: 85 | AJ50: 136 | AK50: 213 | AL50: 298 | AM50: 386 | AN50: 474 | AO50: 543 | AP50: 549 | AQ50: 627 | AR50: 707 | AS50: 788 | AT50: 788
A51: Strex | B51: 8152 | C51: 258 | D51: 5700 | E51: 10832 | F51: 577 | G51: 5100 | H51: 9698 | I51: 350 | J51: 5200 | K51: 46 | L51: 106 | M51: 123 | N51: 149 | O51: 236 | P51: 258 | W51: 108 | X51: 227 | Y51: 320 | Z51: 414 | AA51: 495 | AB51: 577 | AC51: 654 | AD51: 934 | AE51: 934 | AF51: 934 | AG51: 991 | AH51: 930 | AI51: 27 | AJ51: 114 | AK51: 183 | AL51: 266 | AM51: 326 | AN51: 350 | AO51: 388 | AP51: 434 | AQ51: 480 | AR51: 513 | AS51: 557 | AT51: 528

Sheet Wireframe
O5: Actual | P5: 99 / 142 / 198
O6: Budget | P6: 119 / 187 / 226
O7: PY | P7: 204 / 230 / 244
C11: Actual | D11: % PY | E11: % B | G11: Actual | H11: % PY | I11: % B | K11: Actual | L11: % PY | M11: % B
B12: App 1
B13: App 2
B14: App 3
B15: App 4
B16: App 5
B17: App 6
B18: App 7
B19: App 8
B20: App 9
B21: App 10

Sheet Control
C4: INSTRUCTIONS
D6: General
D8: ▪ Select your Point of view from the drop-down box on the dashboard page
D9: ▪ Refresh the data to retrieve from the database
D10: ▪ That's it!
D12: Beware
D14: Do not overwrite the formulas in the Calculation Tab.
D15: Keep protection on for the Dashboard tab to make sure nothing is unintentionally shifted.
D16: Feel free to remove sheet protection. Go to Review and click "unprotect sheet" - there is no password.
C21: Links
D23: Dashboard | F23: Presentation of results
D24: Calculation | F24: Raw preparation for Dashboard
D25: Raw Data | F25: Raw data, retrieved directly from Oracle database
D26: Additional resources | F26: View complete file on intranet (example for internet link)
C30: Version Control
D32: 42955
D33: ▪ Added additional calculations for % columns
D34: ▪ changed KPI sorting to be based on % budget variance instead of full values
D36: 42988
D38: ▪ Included protection
